[{"number":{"inQuran":1213,"inSurah":53},"meta":{"juz":10,"surah":8,"page":184,"manzil":152,"hizbQuarter":73,"sajda":{"recommended":false,"obligatory":false}},"text":{"arab":"\u0630\u0670\u0644\u0650\u0643\u064e \u0628\u0650\u0627\u064e\u0646\u0651\u064e \u0627\u0644\u0644\u0651\u0670\u0647\u064e \u0644\u064e\u0645\u0652 \u064a\u064e\u0643\u064f \u0645\u064f\u063a\u064e\u064a\u0651\u0650\u0631\u064b\u0627 \u0646\u0651\u0650\u0639\u0652\u0645\u064e\u0629\u064b \u0627\u064e\u0646\u0652\u0639\u064e\u0645\u064e\u0647\u064e\u0627 \u0639\u064e\u0644\u0670\u0649 \u0642\u064e\u0648\u0652\u0645\u064d \u062d\u064e\u062a\u0651\u0670\u0649 \u064a\u064f\u063a\u064e\u064a\u0651\u0650\u0631\u064f\u0648\u0652\u0627 \u0645\u064e\u0627 \u0628\u0650\u0627\u064e\u0646\u0652\u0641\u064f\u0633\u0650\u0647\u0650\u0645\u0652\u06d9 \u0648\u064e\u0627\u064e\u0646\u0651\u064e \u0627\u0644\u0644\u0651\u0670\u0647\u064e \u0633\u064e\u0645\u0650\u064a\u0652\u0639\u064c \u0639\u064e\u0644\u0650\u064a\u0652\u0645\u064c\u06d9 ","transliteration":{"en":"Zaalika bi annal laaha lam yaku mughaiyiran ni matan an'amahaa 'alaa qawmin hattaa yughaiyiroo maa bianfusihim wa annallaaha samee un 'Aleem","id":"\u017b\u0101lika bi'annall\u0101ha lam yaku mugayyiran ni\u2018matan an\u2018amah\u0101 \u2018al\u0101 qaumin \u1e25att\u0101 yugayyir\u016b m\u0101 bi'anfusihim, wa annall\u0101ha sam\u012b\u2018un \u2018al\u012bm(un)."}},"translation":{"en":"That is because Allah would not change a favor which He had bestowed upon a people until they change what is within themselves. And indeed, Allah is Hearing and Knowing.","id":"Yang demikian itu karena sesungguhnya Allah tidak akan mengubah suatu nikmat yang telah diberikan-Nya kepada suatu kaum, hingga kaum itu mengubah apa yang ada pada diri mereka sendiri. Sungguh, Allah Maha Mendengar, Maha Mengetahui,"},"audio":{"primary":"https:\/\/cdn.islamic.network\/quran\/audio\/128\/ar.alafasy\/1213.mp3","secondary":["https:\/\/cdn.islamic.network\/quran\/audio\/64\/ar.alafasy\/1213.mp3"]},"tafsir":{"id":{"long":"-","short":"-"}}},{"number":{"inQuran":1214,"inSurah":54},"meta":{"juz":10,"surah":8,"page":184,"manzil":152,"hizbQuarter":73,"sajda":{"recommended":false,"obligatory":false}},"text":{"arab":"\u0643\u064e\u062f\u064e\u0623\u0652\u0628\u0650 \u0627\u0670\u0644\u0650 \u0641\u0650\u0631\u0652\u0639\u064e\u0648\u0652\u0646\u064e\u06d9 \u0648\u064e\u0627\u0644\u0651\u064e\u0630\u0650\u064a\u0652\u0646\u064e \u0645\u0650\u0646\u0652 \u0642\u064e\u0628\u0652\u0644\u0650\u0647\u0650\u0645\u0652\u06da  \u0643\u064e\u0630\u0651\u064e\u0628\u064f\u0648\u0652\u0627 \u0628\u0650\u0627\u0670\u064a\u0670\u062a\u0650 \u0631\u064e\u0628\u0651\u0650\u0647\u0650\u0645\u0652 \u0641\u064e\u0627\u064e\u0647\u0652\u0644\u064e\u0643\u0652\u0646\u0670\u0647\u064f\u0645\u0652 \u0628\u0650\u0630\u064f\u0646\u064f\u0648\u0652\u0628\u0650\u0647\u0650\u0645\u0652 \u0648\u064e\u0627\u064e\u063a\u0652\u0631\u064e\u0642\u0652\u0646\u064e\u0627\u0653 \u0627\u0670\u0644\u064e \u0641\u0650\u0631\u0652\u0639\u064e\u0648\u0652\u0646\u064e\u06da \u0648\u064e\u0643\u064f\u0644\u0651\u064c \u0643\u064e\u0627\u0646\u064f\u0648\u0652\u0627 \u0638\u0670\u0644\u0650\u0645\u0650\u064a\u0652\u0646\u064e ","transliteration":{"en":"Kadaabi Aali Fir'awna wallazeena min qablihim; kazzaboo bi Aayaati Rabbihim faahlaknaahum bizunoobihim wa aghraqnaa Aala Fir'awn; wa kullun kaanoo zaalimeen","id":"kada'bi \u0101li fir\u2018aun(a), wal-la\u017c\u012bna min qablihim, ka\u017c\u017cab\u016b bi'\u0101y\u0101ti rabbihim fa ahlakn\u0101hum bi\u017cun\u016bbihim wa agraqn\u0101 \u0101la fir\u2018aun(a), wa kullun k\u0101n\u016b \u1e93\u0101lim\u012bn(a)."}},"translation":{"en":"[Theirs is] like the custom of the people of Pharaoh and of those before them. They denied the signs of their Lord, so We destroyed them for their sins, and We drowned the people of Pharaoh. And all [of them] were wrongdoers.","id":"(Keadaan mereka) serupa dengan keadaan pengikut Fir\u2018aun dan orang-orang yang sebelum mereka. Mereka mendustakan ayat-ayat Tuhannya, maka Kami membinasakan mereka disebabkan oleh dosa-dosanya dan Kami tenggelamkan Fir\u2018aun dan pengikut-pengikutnya; karena mereka adalah orang-orang yang zalim."},"audio":{"primary":"https:\/\/cdn.islamic.network\/quran\/audio\/128\/ar.alafasy\/1214.mp3","secondary":["https:\/\/cdn.islamic.network\/quran\/audio\/64\/ar.alafasy\/1214.mp3"]},"tafsir":{"id":{"long":"-","short":"-"}}},{"number":{"inQuran":1215,"inSurah":55},"meta":{"juz":10,"surah":8,"page":184,"manzil":152,"hizbQuarter":73,"sajda":{"recommended":false,"obligatory":false}},"text":{"arab":"\u0627\u0650\u0646\u0651\u064e \u0634\u064e\u0631\u0651\u064e \u0627\u0644\u062f\u0651\u064e\u0648\u064e\u0627\u06e4\u0628\u0651\u0650 \u0639\u0650\u0646\u0652\u062f\u064e \u0627\u0644\u0644\u0651\u0670\u0647\u0650 \u0627\u0644\u0651\u064e\u0630\u0650\u064a\u0652\u0646\u064e \u0643\u064e\u0641\u064e\u0631\u064f\u0648\u0652\u0627 \u0641\u064e\u0647\u064f\u0645\u0652 \u0644\u064e\u0627 \u064a\u064f\u0624\u0652\u0645\u0650\u0646\u064f\u0648\u0652\u0646\u064e\u06d6 ","transliteration":{"en":"Inna sharrad dawaaabbi 'indal laahil lazeena kafaroo fahum laa yu'minoon","id":"inna syarrad-daw\u0101bbi \u2018indall\u0101hil-la\u017c\u012bna kafar\u016b fahum l\u0101 yu'min\u016bn(a)."}},"translation":{"en":"Indeed, the worst of living creatures in the sight of Allah are those who have disbelieved, and they will not [ever] believe -","id":"Sesungguhnya makhluk bergerak yang bernyawa yang paling buruk dalam pandangan Allah ialah orang-orang kafir, karena mereka tidak beriman."},"audio":{"primary":"https:\/\/cdn.islamic.network\/quran\/audio\/128\/ar.alafasy\/1215.mp3","secondary":["https:\/\/cdn.islamic.network\/quran\/audio\/64\/ar.alafasy\/1215.mp3"]},"tafsir":{"id":{"long":"-","short":"-"}}},{"number":{"inQuran":1216,"inSurah":56},"meta":{"juz":10,"surah":8,"page":184,"manzil":152,"hizbQuarter":73,"sajda":{"recommended":false,"obligatory":false}},"text":{"arab":"\u0627\u0644\u0651\u064e\u0630\u0650\u064a\u0652\u0646\u064e \u0639\u064e\u0627\u0647\u064e\u062f\u0652\u062a\u0651\u064e \u0645\u0650\u0646\u0652\u0647\u064f\u0645\u0652 \u062b\u064f\u0645\u0651\u064e \u064a\u064e\u0646\u0652\u0642\u064f\u0636\u064f\u0648\u0652\u0646\u064e \u0639\u064e\u0647\u0652\u062f\u064e\u0647\u064f\u0645\u0652 \u0641\u0650\u064a\u0652 \u0643\u064f\u0644\u0651\u0650 \u0645\u064e\u0631\u0651\u064e\u0629\u064d \u0648\u0651\u064e\u0647\u064f\u0645\u0652 \u0644\u064e\u0627 \u064a\u064e\u062a\u0651\u064e\u0642\u064f\u0648\u0652\u0646\u064e ","transliteration":{"en":"Allazeena'aahatta min hum summa yanqudoona 'ahdahum fee kulli marratinw wa hum laa yattaqoon","id":"alla\u017c\u012bna \u2018\u0101hatta minhum \u1e61umma yanqu\u1e0d\u016bna \u2018ahdahum f\u012b kulli marratiw wa hum l\u0101 yattaq\u016bn(a)."}},"translation":{"en":"The ones with whom you made a treaty but then they break their pledge every time, and they do not fear Allah.","id":"(Yaitu) orang-orang yang terikat perjanjian dengan kamu, kemudian setiap kali berjanji mereka mengkhianati janjinya, sedang mereka tidak takut (kepada Allah)."},"audio":{"primary":"https:\/\/cdn.islamic.network\/quran\/audio\/128\/ar.alafasy\/1216.mp3","secondary":["https:\/\/cdn.islamic.network\/quran\/audio\/64\/ar.alafasy\/1216.mp3"]},"tafsir":{"id":{"long":"-","short":"-"}}},{"number":{"inQuran":1217,"inSurah":57},"meta":{"juz":10,"surah":8,"page":184,"manzil":152,"hizbQuarter":73,"sajda":{"recommended":false,"obligatory":false}},"text":{"arab":"\u0641\u064e\u0627\u0650\u0645\u0651\u064e\u0627 \u062a\u064e\u062b\u0652\u0642\u064e\u0641\u064e\u0646\u0651\u064e\u0647\u064f\u0645\u0652 \u0641\u0650\u0649 \u0627\u0644\u0652\u062d\u064e\u0631\u0652\u0628\u0650 \u0641\u064e\u0634\u064e\u0631\u0651\u0650\u062f\u0652 \u0628\u0650\u0647\u0650\u0645\u0652 \u0645\u0651\u064e\u0646\u0652 \u062e\u064e\u0644\u0652\u0641\u064e\u0647\u064f\u0645\u0652 \u0644\u064e\u0639\u064e\u0644\u0651\u064e\u0647\u064f\u0645\u0652 \u064a\u064e\u0630\u0651\u064e\u0643\u0651\u064e\u0631\u064f\u0648\u0652\u0646\u064e ","transliteration":{"en":"Fa immaa tasqafannahum fil harbi fasharrid bihim man khalfahum la'allahum yazzakkaroon","id":"fa imm\u0101 ta\u1e61qafannahum fil-\u1e25arbi fa syarrid bihim man khalfahum la\u2018allahum ya\u017c\u017cakkar\u016bn(a)."}},"translation":{"en":"So if you, [O Muhammad], gain dominance over them in war, disperse by [means of] them those behind them that perhaps they will be reminded.","id":"Maka jika engkau (Muhammad) mengungguli mereka dalam peperangan, maka cerai-beraikanlah orang-orang yang di belakang mereka dengan (menumpas) mereka, agar mereka mengambil pelajaran."},"audio":{"primary":"https:\/\/cdn.islamic.network\/quran\/audio\/128\/ar.alafasy\/1217.mp3","secondary":["https:\/\/cdn.islamic.network\/quran\/audio\/64\/ar.alafasy\/1217.mp3"]},"tafsir":{"id":{"long":"-","short":"-"}}},{"number":{"inQuran":1218,"inSurah":58},"meta":{"juz":10,"surah":8,"page":184,"manzil":152,"hizbQuarter":73,"sajda":{"recommended":false,"obligatory":false}},"text":{"arab":"\u0648\u064e\u0627\u0650\u0645\u0651\u064e\u0627 \u062a\u064e\u062e\u064e\u0627\u0641\u064e\u0646\u0651\u064e \u0645\u0650\u0646\u0652 \u0642\u064e\u0648\u0652\u0645\u064d \u062e\u0650\u064a\u064e\u0627\u0646\u064e\u0629\u064b \u0641\u064e\u0627\u0646\u0652\u06e2\u0628\u0650\u0630\u0652 \u0627\u0650\u0644\u064e\u064a\u0652\u0647\u0650\u0645\u0652 \u0639\u064e\u0644\u0670\u0649 \u0633\u064e\u0648\u064e\u0627\u06e4\u0621\u064d\u06d7 \u0627\u0650\u0646\u0651\u064e \u0627\u0644\u0644\u0651\u0670\u0647\u064e \u0644\u064e\u0627 \u064a\u064f\u062d\u0650\u0628\u0651\u064f \u0627\u0644\u0652\u062e\u064e\u0627\u06e4\u0649\u0655\u0650\u0646\u0650\u064a\u0652\u0646\u064e \u08d6 ","transliteration":{"en":"Wa immaa takhaafana min qawmin khiyaanatan fambiz ilaihim 'alaa sawaaa'; innal laaha laayuhibbul khaaa'ineen","id":"wa imm\u0101 takh\u0101fanna min qaumin khiy\u0101natan fambi\u017c ilaihim \u2018al\u0101 saw\u0101'(in), innall\u0101ha l\u0101 yu\u1e25ibbul-kh\u0101'in\u012bn(a)."}},"translation":{"en":"If you [have reason to] fear from a people betrayal, throw [their treaty] back to them, [putting you] on equal terms. Indeed, Allah does not like traitors.","id":"Dan jika engkau (Muhammad) khawatir akan (terjadinya) pengkhianatan dari suatu golongan, maka kembalikanlah perjanjian itu kepada mereka dengan cara yang jujur. Sungguh, Allah tidak menyukai orang yang berkhianat."},"audio":{"primary":"https:\/\/cdn.islamic.network\/quran\/audio\/128\/ar.alafasy\/1218.mp3","secondary":["https:\/\/cdn.islamic.network\/quran\/audio\/64\/ar.alafasy\/1218.mp3"]},"tafsir":{"id":{"long":"-","short":"-"}}},{"number":{"inQuran":1219,"inSurah":59},"meta":{"juz":10,"surah":8,"page":184,"manzil":153,"hizbQuarter":73,"sajda":{"recommended":false,"obligatory":false}},"text":{"arab":"\u0648\u064e\u0644\u064e\u0627 \u064a\u064e\u062d\u0652\u0633\u064e\u0628\u064e\u0646\u0651\u064e \u0627\u0644\u0651\u064e\u0630\u0650\u064a\u0652\u0646\u064e \u0643\u064e\u0641\u064e\u0631\u064f\u0648\u0652\u0627 \u0633\u064e\u0628\u064e\u0642\u064f\u0648\u0652\u0627\u06d7 \u0627\u0650\u0646\u0651\u064e\u0647\u064f\u0645\u0652 \u0644\u064e\u0627 \u064a\u064f\u0639\u0652\u062c\u0650\u0632\u064f\u0648\u0652\u0646\u064e ","transliteration":{"en":"Wa laa yahsabannal lazeena kafaroo sabaqooo; innahum laa yu'jizoon","id":"wa l\u0101 ya\u1e25sabannal-la\u017c\u012bna kafar\u016b sabaq\u016b, innahum l\u0101 yu\u2018jiz\u016bn(a)."}},"translation":{"en":"And let not those who disbelieve think they will escape. Indeed, they will not cause failure [to Allah].","id":"Dan janganlah orang-orang kafir mengira, bahwa mereka akan dapat lolos (dari kekuasaan Allah). Sungguh, mereka tidak dapat melemahkan (Allah)."},"audio":{"primary":"https:\/\/cdn.islamic.network\/quran\/audio\/128\/ar.alafasy\/1219.mp3","secondary":["https:\/\/cdn.islamic.network\/quran\/audio\/64\/ar.alafasy\/1219.mp3"]},"tafsir":{"id":{"long":"-","short":"-"}}},{"number":{"inQuran":1220,"inSurah":60},"meta":{"juz":10,"surah":8,"page":184,"manzil":153,"hizbQuarter":73,"sajda":{"recommended":false,"obligatory":false}},"text":{"arab":"\u0648\u064e\u0627\u064e\u0639\u0650\u062f\u0651\u064f\u0648\u0652\u0627 \u0644\u064e\u0647\u064f\u0645\u0652 \u0645\u0651\u064e\u0627 \u0627\u0633\u0652\u062a\u064e\u0637\u064e\u0639\u0652\u062a\u064f\u0645\u0652 \u0645\u0651\u0650\u0646\u0652 \u0642\u064f\u0648\u0651\u064e\u0629\u064d \u0648\u0651\u064e\u0645\u0650\u0646\u0652 \u0631\u0651\u0650\u0628\u064e\u0627\u0637\u0650 \u0627\u0644\u0652\u062e\u064e\u064a\u0652\u0644\u0650 \u062a\u064f\u0631\u0652\u0647\u0650\u0628\u064f\u0648\u0652\u0646\u064e \u0628\u0650\u0647\u0656 \u0639\u064e\u062f\u064f\u0648\u0651\u064e \u0627\u0644\u0644\u0651\u0670\u0647\u0650 \u0648\u064e\u0639\u064e\u062f\u064f\u0648\u0651\u064e\u0643\u064f\u0645\u0652 \u0648\u064e\u0627\u0670\u062e\u064e\u0631\u0650\u064a\u0652\u0646\u064e \u0645\u0650\u0646\u0652 \u062f\u064f\u0648\u0652\u0646\u0650\u0647\u0650\u0645\u0652\u06da  \u0644\u064e\u0627 \u062a\u064e\u0639\u0652\u0644\u064e\u0645\u064f\u0648\u0652\u0646\u064e\u0647\u064f\u0645\u0652\u06da  \u0627\u064e\u0644\u0644\u0651\u0670\u0647\u064f \u064a\u064e\u0639\u0652\u0644\u064e\u0645\u064f\u0647\u064f\u0645\u0652\u06d7 \u0648\u064e\u0645\u064e\u0627 \u062a\u064f\u0646\u0652\u0641\u0650\u0642\u064f\u0648\u0652\u0627 \u0645\u0650\u0646\u0652 \u0634\u064e\u064a\u0652\u0621\u064d \u0641\u0650\u064a\u0652 \u0633\u064e\u0628\u0650\u064a\u0652\u0644\u0650 \u0627\u0644\u0644\u0651\u0670\u0647\u0650 \u064a\u064f\u0648\u064e\u0641\u0651\u064e \u0627\u0650\u0644\u064e\u064a\u0652\u0643\u064f\u0645\u0652 \u0648\u064e\u0627\u064e\u0646\u0652\u062a\u064f\u0645\u0652 \u0644\u064e\u0627 \u062a\u064f\u0638\u0652\u0644\u064e\u0645\u064f\u0648\u0652\u0646\u064e ","transliteration":{"en":"Wa a'iddoo lahum mastata'tum min quwwatinw wa mirribaatil khaili turhiboona bihee 'aduwwal laahi wa 'aduwwakum wa aakhareena min doonihim laa ta'lamoo nahum Allaahu ya'lamuhum; wa maa tunfiqoo min shai'in fee sabeelil laahi yuwaf failaikum wa antum laa tuzlamoon","id":"wa a\u2018idd\u016b lahum masta\u1e6da\u2018tum min quwwatiw wa mir rib\u0101\u1e6dil-khaili turhib\u016bna bih\u012b \u2018aduwwall\u0101hi wa \u2018aduwwakum wa \u0101khar\u012bna min d\u016bnihim, l\u0101 ta\u2018lam\u016bnahum, all\u0101hu ya\u2018lamuhum, wa m\u0101 tunfiq\u016b min syai'in f\u012b sab\u012blill\u0101hi yuwaffa ilaikum wa antum l\u0101 tu\u1e93lam\u016bn(a)."}},"translation":{"en":"And prepare against them whatever you are able of power and of steeds of war by which you may terrify the enemy of Allah and your enemy and others besides them whom you do not know [but] whom Allah knows. And whatever you spend in the cause of Allah will be fully repaid to you, and you will not be wronged.","id":"Dan persiapkanlah dengan segala kemampuan untuk menghadapi mereka dengan kekuatan yang kamu miliki dan dari pasukan berkuda yang dapat menggentarkan musuh Allah, musuhmu dan orang-orang selain mereka yang kamu tidak mengetahuinya; tetapi Allah mengetahuinya. Apa saja yang kamu infakkan di jalan Allah niscaya akan dibalas dengan cukup kepadamu dan kamu tidak akan dizalimi (dirugikan)."},"audio":{"primary":"https:\/\/cdn.islamic.network\/quran\/audio\/128\/ar.alafasy\/1220.mp3","secondary":["https:\/\/cdn.islamic.network\/quran\/audio\/64\/ar.alafasy\/1220.mp3"]},"tafsir":{"id":{"long":"-","short":"-"}}},{"number":{"inQuran":1221,"inSurah":61},"meta":{"juz":10,"surah":8,"page":184,"manzil":153,"hizbQuarter":74,"sajda":{"recommended":false,"obligatory":false}},"text":{"arab":"\u06de \u0648\u064e\u0627\u0650\u0646\u0652 \u062c\u064e\u0646\u064e\u062d\u064f\u0648\u0652\u0627 \u0644\u0650\u0644\u0633\u0651\u064e\u0644\u0652\u0645\u0650 \u0641\u064e\u0627\u062c\u0652\u0646\u064e\u062d\u0652 \u0644\u064e\u0647\u064e\u0627 \u0648\u064e\u062a\u064e\u0648\u064e\u0643\u0651\u064e\u0644\u0652 \u0639\u064e\u0644\u064e\u0649 \u0627\u0644\u0644\u0651\u0670\u0647\u0650 \u06d7\u0627\u0650\u0646\u0651\u064e\u0647\u0657 \u0647\u064f\u0648\u064e \u0627\u0644\u0633\u0651\u064e\u0645\u0650\u064a\u0652\u0639\u064f \u0627\u0644\u0652\u0639\u064e\u0644\u0650\u064a\u0652\u0645\u064f ","transliteration":{"en":"Wa in janahoo lissalmi fajnah lahaa wa tawakkal 'alal laah; innahoo Huwas Samee'ul 'Aleem","id":"wa in jana\u1e25\u016b lis-salmi fajna\u1e25 lah\u0101 wa tawakkal \u2018alall\u0101h(i), innah\u016b huwas-sam\u012b\u2018ul-\u2018al\u012bm(u)."}},"translation":{"en":"And if they incline to peace, then incline to it [also] and rely upon Allah. Indeed, it is He who is the Hearing, the Knowing.","id":"Tetapi jika mereka condong kepada perdamaian, maka terimalah dan bertawakallah kepada Allah. Sungguh, Dia Maha Mendengar, Maha Mengetahui."},"audio":{"primary":"https:\/\/cdn.islamic.network\/quran\/audio\/128\/ar.alafasy\/1221.mp3","secondary":["https:\/\/cdn.islamic.network\/quran\/audio\/64\/ar.alafasy\/1221.mp3"]},"tafsir":{"id":{"long":"-","short":"-"}}}]