[{"number":{"inQuran":3813,"inSurah":25},"meta":{"juz":23,"page":447,"manzil":6,"ruku":387,"hizbQuarter":179,"sajda":{"recommended":false,"obligatory":false}},"surah":{"number":37,"sequence":56,"numberOfVerses":182,"name":{"short":"\u0627\u0644\u0635\u0627\u0641\u0627\u062a","long":"\u0627\u0644\u0635\u0627\u0641\u0627\u062a","transliteration":{"en":"As-Saffat","id":"As-Saffat"},"translation":{"en":"Those who set the Ranks","id":"Barisan-barisan"}},"bismillah_pre":true,"preBismillah":{"preBismillah":{"text":{"arab":"\u0628\u0650\u0633\u0652\u0645\u0650 \u0627\u0644\u0644\u0651\u064e\u0647\u0650 \u0627\u0644\u0631\u0651\u064e\u062d\u0652\u0645\u064e\u0670\u0646\u0650 \u0627\u0644\u0631\u0651\u064e\u062d\u0650\u064a\u0645\u0650","transliteration":{"en":"Bismillaahir Rahmaanir Raheem"}},"translation":{"en":"In the name of Allah, the Entirely Merciful, the Especially Merciful.","id":"Dengan nama Allah Yang Maha Pengasih, Maha Penyayang."},"audio":{"primary":"https:\/\/cdn.alquran.cloud\/media\/audio\/ayah\/ar.alafasy\/1","secondary":["https:\/\/cdn.islamic.network\/quran\/audio\/128\/ar.alafasy\/1.mp3","https:\/\/cdn.islamic.network\/quran\/audio\/64\/ar.alafasy\/1.mp3"]}}},"relevation":{"arab":"\u0645\u0643\u0629","en":"Meccan","id":"Makkiyyah"},"tafsir":{"en":"TBD","id":"TBD"}},"text":{"arab":"\u0645\u064e\u0627 \u0644\u064e\u0643\u064f\u0645\u0652 \u0644\u064e\u0627 \u062a\u064e\u0646\u064e\u0627\u0635\u064e\u0631\u064f\u0648\u0652\u0646\u064e ","transliteration":{"en":"Maa lakum laa tanaasaroon","id":"M\u0101 lakum l\u0101 tan\u0101\u1e63ar\u016bn(a)."}},"translation":{"en":"[They will be asked], \"What is [wrong] with you? Why do you not help each other?\"","id":"\"Kenapa kamu tidak tolong menolong?\""},"audio":{"primary":"https:\/\/cdn.islamic.network\/quran\/audio\/128\/ar.alafasy\/3813.mp3","secondary":["https:\/\/cdn.islamic.network\/quran\/audio\/64\/ar.alafasy\/3813.mp3"]},"tafsir":{"id":{"short":"-","long":"-"}}},{"number":{"inQuran":3814,"inSurah":26},"meta":{"juz":23,"page":447,"manzil":6,"ruku":387,"hizbQuarter":179,"sajda":{"recommended":false,"obligatory":false}},"surah":{"number":37,"sequence":56,"numberOfVerses":182,"name":{"short":"\u0627\u0644\u0635\u0627\u0641\u0627\u062a","long":"\u0627\u0644\u0635\u0627\u0641\u0627\u062a","transliteration":{"en":"As-Saffat","id":"As-Saffat"},"translation":{"en":"Those who set the Ranks","id":"Barisan-barisan"}},"bismillah_pre":true,"preBismillah":{"preBismillah":{"text":{"arab":"\u0628\u0650\u0633\u0652\u0645\u0650 \u0627\u0644\u0644\u0651\u064e\u0647\u0650 \u0627\u0644\u0631\u0651\u064e\u062d\u0652\u0645\u064e\u0670\u0646\u0650 \u0627\u0644\u0631\u0651\u064e\u062d\u0650\u064a\u0645\u0650","transliteration":{"en":"Bismillaahir Rahmaanir Raheem"}},"translation":{"en":"In the name of Allah, the Entirely Merciful, the Especially Merciful.","id":"Dengan nama Allah Yang Maha Pengasih, Maha Penyayang."},"audio":{"primary":"https:\/\/cdn.alquran.cloud\/media\/audio\/ayah\/ar.alafasy\/1","secondary":["https:\/\/cdn.islamic.network\/quran\/audio\/128\/ar.alafasy\/1.mp3","https:\/\/cdn.islamic.network\/quran\/audio\/64\/ar.alafasy\/1.mp3"]}}},"relevation":{"arab":"\u0645\u0643\u0629","en":"Meccan","id":"Makkiyyah"},"tafsir":{"en":"TBD","id":"TBD"}},"text":{"arab":"\u0628\u064e\u0644\u0652 \u0647\u064f\u0645\u064f \u0627\u0644\u0652\u064a\u064e\u0648\u0652\u0645\u064e \u0645\u064f\u0633\u0652\u062a\u064e\u0633\u0652\u0644\u0650\u0645\u064f\u0648\u0652\u0646\u064e","transliteration":{"en":"Bal humul Yawma mustaslimoon","id":"Bal humul-yauma mustaslim\u016bn(a)."}},"translation":{"en":"But they, that Day, are in surrender.","id":"Bahkan mereka pada hari itu menyerah diri."},"audio":{"primary":"https:\/\/cdn.islamic.network\/quran\/audio\/128\/ar.alafasy\/3814.mp3","secondary":["https:\/\/cdn.islamic.network\/quran\/audio\/64\/ar.alafasy\/3814.mp3"]},"tafsir":{"id":{"short":"-","long":"-"}}},{"number":{"inQuran":3815,"inSurah":27},"meta":{"juz":23,"page":447,"manzil":6,"ruku":387,"hizbQuarter":179,"sajda":{"recommended":false,"obligatory":false}},"surah":{"number":37,"sequence":56,"numberOfVerses":182,"name":{"short":"\u0627\u0644\u0635\u0627\u0641\u0627\u062a","long":"\u0627\u0644\u0635\u0627\u0641\u0627\u062a","transliteration":{"en":"As-Saffat","id":"As-Saffat"},"translation":{"en":"Those who set the Ranks","id":"Barisan-barisan"}},"bismillah_pre":true,"preBismillah":{"preBismillah":{"text":{"arab":"\u0628\u0650\u0633\u0652\u0645\u0650 \u0627\u0644\u0644\u0651\u064e\u0647\u0650 \u0627\u0644\u0631\u0651\u064e\u062d\u0652\u0645\u064e\u0670\u0646\u0650 \u0627\u0644\u0631\u0651\u064e\u062d\u0650\u064a\u0645\u0650","transliteration":{"en":"Bismillaahir Rahmaanir Raheem"}},"translation":{"en":"In the name of Allah, the Entirely Merciful, the Especially Merciful.","id":"Dengan nama Allah Yang Maha Pengasih, Maha Penyayang."},"audio":{"primary":"https:\/\/cdn.alquran.cloud\/media\/audio\/ayah\/ar.alafasy\/1","secondary":["https:\/\/cdn.islamic.network\/quran\/audio\/128\/ar.alafasy\/1.mp3","https:\/\/cdn.islamic.network\/quran\/audio\/64\/ar.alafasy\/1.mp3"]}}},"relevation":{"arab":"\u0645\u0643\u0629","en":"Meccan","id":"Makkiyyah"},"tafsir":{"en":"TBD","id":"TBD"}},"text":{"arab":"\u0648\u064e\u0627\u064e\u0642\u0652\u0628\u064e\u0644\u064e \u0628\u064e\u0639\u0652\u0636\u064f\u0647\u064f\u0645\u0652 \u0639\u064e\u0644\u0670\u0649 \u0628\u064e\u0639\u0652\u0636\u064d \u064a\u0651\u064e\u062a\u064e\u0633\u064e\u0627\u06e4\u0621\u064e\u0644\u064f\u0648\u0652\u0646\u064e ","transliteration":{"en":"Wa aqbala ba'duhum 'alaa ba'diny yatasaaa'aloon","id":"Wa aqbala ba\u2018\u1e0duhum \u2018al\u0101 ba\u2018\u1e0diy yatas\u0101'al\u016bn(a)."}},"translation":{"en":"And they will approach one another blaming each other.","id":"Sebahagian dan mereka menghadap kepada sebahagian yang lain berbantah-bantahan."},"audio":{"primary":"https:\/\/cdn.islamic.network\/quran\/audio\/128\/ar.alafasy\/3815.mp3","secondary":["https:\/\/cdn.islamic.network\/quran\/audio\/64\/ar.alafasy\/3815.mp3"]},"tafsir":{"id":{"short":"-","long":"-"}}},{"number":{"inQuran":3816,"inSurah":28},"meta":{"juz":23,"page":447,"manzil":6,"ruku":387,"hizbQuarter":179,"sajda":{"recommended":false,"obligatory":false}},"surah":{"number":37,"sequence":56,"numberOfVerses":182,"name":{"short":"\u0627\u0644\u0635\u0627\u0641\u0627\u062a","long":"\u0627\u0644\u0635\u0627\u0641\u0627\u062a","transliteration":{"en":"As-Saffat","id":"As-Saffat"},"translation":{"en":"Those who set the Ranks","id":"Barisan-barisan"}},"bismillah_pre":true,"preBismillah":{"preBismillah":{"text":{"arab":"\u0628\u0650\u0633\u0652\u0645\u0650 \u0627\u0644\u0644\u0651\u064e\u0647\u0650 \u0627\u0644\u0631\u0651\u064e\u062d\u0652\u0645\u064e\u0670\u0646\u0650 \u0627\u0644\u0631\u0651\u064e\u062d\u0650\u064a\u0645\u0650","transliteration":{"en":"Bismillaahir Rahmaanir Raheem"}},"translation":{"en":"In the name of Allah, the Entirely Merciful, the Especially Merciful.","id":"Dengan nama Allah Yang Maha Pengasih, Maha Penyayang."},"audio":{"primary":"https:\/\/cdn.alquran.cloud\/media\/audio\/ayah\/ar.alafasy\/1","secondary":["https:\/\/cdn.islamic.network\/quran\/audio\/128\/ar.alafasy\/1.mp3","https:\/\/cdn.islamic.network\/quran\/audio\/64\/ar.alafasy\/1.mp3"]}}},"relevation":{"arab":"\u0645\u0643\u0629","en":"Meccan","id":"Makkiyyah"},"tafsir":{"en":"TBD","id":"TBD"}},"text":{"arab":"\u0642\u064e\u0627\u0644\u064f\u0648\u0652\u0653\u0627 \u0627\u0650\u0646\u0651\u064e\u0643\u064f\u0645\u0652 \u0643\u064f\u0646\u0652\u062a\u064f\u0645\u0652 \u062a\u064e\u0623\u0652\u062a\u064f\u0648\u0652\u0646\u064e\u0646\u064e\u0627 \u0639\u064e\u0646\u0650 \u0627\u0644\u0652\u064a\u064e\u0645\u0650\u064a\u0652\u0646\u0650 ","transliteration":{"en":"Qaalooo innakum kuntum taatoonanaa 'anil yameen","id":"Q\u0101l\u016b innakum kuntum ta't\u016bnan\u0101 \u2018anil-yam\u012bn(i)."}},"translation":{"en":"They will say, \"Indeed, you used to come at us from the right.\"","id":"Pengikut-pengikut mereka berkata (kepada pemimpin-pemimpin mereka): \"Sesungguhnya kamulah yang datang kepada kami dan kanan."},"audio":{"primary":"https:\/\/cdn.islamic.network\/quran\/audio\/128\/ar.alafasy\/3816.mp3","secondary":["https:\/\/cdn.islamic.network\/quran\/audio\/64\/ar.alafasy\/3816.mp3"]},"tafsir":{"id":{"short":"-","long":"-"}}},{"number":{"inQuran":3817,"inSurah":29},"meta":{"juz":23,"page":447,"manzil":6,"ruku":387,"hizbQuarter":179,"sajda":{"recommended":false,"obligatory":false}},"surah":{"number":37,"sequence":56,"numberOfVerses":182,"name":{"short":"\u0627\u0644\u0635\u0627\u0641\u0627\u062a","long":"\u0627\u0644\u0635\u0627\u0641\u0627\u062a","transliteration":{"en":"As-Saffat","id":"As-Saffat"},"translation":{"en":"Those who set the Ranks","id":"Barisan-barisan"}},"bismillah_pre":true,"preBismillah":{"preBismillah":{"text":{"arab":"\u0628\u0650\u0633\u0652\u0645\u0650 \u0627\u0644\u0644\u0651\u064e\u0647\u0650 \u0627\u0644\u0631\u0651\u064e\u062d\u0652\u0645\u064e\u0670\u0646\u0650 \u0627\u0644\u0631\u0651\u064e\u062d\u0650\u064a\u0645\u0650","transliteration":{"en":"Bismillaahir Rahmaanir Raheem"}},"translation":{"en":"In the name of Allah, the Entirely Merciful, the Especially Merciful.","id":"Dengan nama Allah Yang Maha Pengasih, Maha Penyayang."},"audio":{"primary":"https:\/\/cdn.alquran.cloud\/media\/audio\/ayah\/ar.alafasy\/1","secondary":["https:\/\/cdn.islamic.network\/quran\/audio\/128\/ar.alafasy\/1.mp3","https:\/\/cdn.islamic.network\/quran\/audio\/64\/ar.alafasy\/1.mp3"]}}},"relevation":{"arab":"\u0645\u0643\u0629","en":"Meccan","id":"Makkiyyah"},"tafsir":{"en":"TBD","id":"TBD"}},"text":{"arab":"\u0642\u064e\u0627\u0644\u064f\u0648\u0652\u0627 \u0628\u064e\u0644\u0652 \u0644\u0651\u064e\u0645\u0652 \u062a\u064e\u0643\u064f\u0648\u0652\u0646\u064f\u0648\u0652\u0627 \u0645\u064f\u0624\u0652\u0645\u0650\u0646\u0650\u064a\u0652\u0646\u064e\u06da ","transliteration":{"en":"Qaaloo bal lam takoonoo mu'mineen","id":"Q\u0101l\u016b bal lam tak\u016bn\u016b mu'min\u012bn(a)."}},"translation":{"en":"The oppressors will say, \"Rather, you [yourselves] were not believers,","id":"Pemimpin-pemimpin mereka menjawab: \"Sebenarnya kamulah yang tidak beriman\"."},"audio":{"primary":"https:\/\/cdn.islamic.network\/quran\/audio\/128\/ar.alafasy\/3817.mp3","secondary":["https:\/\/cdn.islamic.network\/quran\/audio\/64\/ar.alafasy\/3817.mp3"]},"tafsir":{"id":{"short":"-","long":"-"}}},{"number":{"inQuran":3818,"inSurah":30},"meta":{"juz":23,"page":447,"manzil":6,"ruku":387,"hizbQuarter":179,"sajda":{"recommended":false,"obligatory":false}},"surah":{"number":37,"sequence":56,"numberOfVerses":182,"name":{"short":"\u0627\u0644\u0635\u0627\u0641\u0627\u062a","long":"\u0627\u0644\u0635\u0627\u0641\u0627\u062a","transliteration":{"en":"As-Saffat","id":"As-Saffat"},"translation":{"en":"Those who set the Ranks","id":"Barisan-barisan"}},"bismillah_pre":true,"preBismillah":{"preBismillah":{"text":{"arab":"\u0628\u0650\u0633\u0652\u0645\u0650 \u0627\u0644\u0644\u0651\u064e\u0647\u0650 \u0627\u0644\u0631\u0651\u064e\u062d\u0652\u0645\u064e\u0670\u0646\u0650 \u0627\u0644\u0631\u0651\u064e\u062d\u0650\u064a\u0645\u0650","transliteration":{"en":"Bismillaahir Rahmaanir Raheem"}},"translation":{"en":"In the name of Allah, the Entirely Merciful, the Especially Merciful.","id":"Dengan nama Allah Yang Maha Pengasih, Maha Penyayang."},"audio":{"primary":"https:\/\/cdn.alquran.cloud\/media\/audio\/ayah\/ar.alafasy\/1","secondary":["https:\/\/cdn.islamic.network\/quran\/audio\/128\/ar.alafasy\/1.mp3","https:\/\/cdn.islamic.network\/quran\/audio\/64\/ar.alafasy\/1.mp3"]}}},"relevation":{"arab":"\u0645\u0643\u0629","en":"Meccan","id":"Makkiyyah"},"tafsir":{"en":"TBD","id":"TBD"}},"text":{"arab":"\u0648\u064e\u0645\u064e\u0627 \u0643\u064e\u0627\u0646\u064e \u0644\u064e\u0646\u064e\u0627 \u0639\u064e\u0644\u064e\u064a\u0652\u0643\u064f\u0645\u0652 \u0645\u0651\u0650\u0646\u0652 \u0633\u064f\u0644\u0652\u0637\u0670\u0646\u064d\u06da \u0628\u064e\u0644\u0652 \u0643\u064f\u0646\u0652\u062a\u064f\u0645\u0652 \u0642\u064e\u0648\u0652\u0645\u064b\u0627 \u0637\u0670\u063a\u0650\u064a\u0652\u0646\u064e ","transliteration":{"en":"Wa maa kaana lanaa 'alaikum min sultaanim bal kuntum qawman taagheen","id":"Wa m\u0101 k\u0101na lan\u0101 \u2018alaikum min sul\u1e6d\u0101n(in), bal kuntum qauman \u1e6d\u0101g\u012bn(a)."}},"translation":{"en":"And we had over you no authority, but you were a transgressing people.","id":"Dan sekali-kali kami tidak berkuasa terhadapmu, bahkan kamulah kaum yang melampaui batas."},"audio":{"primary":"https:\/\/cdn.islamic.network\/quran\/audio\/128\/ar.alafasy\/3818.mp3","secondary":["https:\/\/cdn.islamic.network\/quran\/audio\/64\/ar.alafasy\/3818.mp3"]},"tafsir":{"id":{"short":"-","long":"-"}}},{"number":{"inQuran":3819,"inSurah":31},"meta":{"juz":23,"page":447,"manzil":6,"ruku":387,"hizbQuarter":179,"sajda":{"recommended":false,"obligatory":false}},"surah":{"number":37,"sequence":56,"numberOfVerses":182,"name":{"short":"\u0627\u0644\u0635\u0627\u0641\u0627\u062a","long":"\u0627\u0644\u0635\u0627\u0641\u0627\u062a","transliteration":{"en":"As-Saffat","id":"As-Saffat"},"translation":{"en":"Those who set the Ranks","id":"Barisan-barisan"}},"bismillah_pre":true,"preBismillah":{"preBismillah":{"text":{"arab":"\u0628\u0650\u0633\u0652\u0645\u0650 \u0627\u0644\u0644\u0651\u064e\u0647\u0650 \u0627\u0644\u0631\u0651\u064e\u062d\u0652\u0645\u064e\u0670\u0646\u0650 \u0627\u0644\u0631\u0651\u064e\u062d\u0650\u064a\u0645\u0650","transliteration":{"en":"Bismillaahir Rahmaanir Raheem"}},"translation":{"en":"In the name of Allah, the Entirely Merciful, the Especially Merciful.","id":"Dengan nama Allah Yang Maha Pengasih, Maha Penyayang."},"audio":{"primary":"https:\/\/cdn.alquran.cloud\/media\/audio\/ayah\/ar.alafasy\/1","secondary":["https:\/\/cdn.islamic.network\/quran\/audio\/128\/ar.alafasy\/1.mp3","https:\/\/cdn.islamic.network\/quran\/audio\/64\/ar.alafasy\/1.mp3"]}}},"relevation":{"arab":"\u0645\u0643\u0629","en":"Meccan","id":"Makkiyyah"},"tafsir":{"en":"TBD","id":"TBD"}},"text":{"arab":"\u0641\u064e\u062d\u064e\u0642\u0651\u064e \u0639\u064e\u0644\u064e\u064a\u0652\u0646\u064e\u0627 \u0642\u064e\u0648\u0652\u0644\u064f \u0631\u064e\u0628\u0651\u0650\u0646\u064e\u0627\u0653  \u06d6\u0627\u0650\u0646\u0651\u064e\u0627 \u0644\u064e\u0630\u064e\u0627\u06e4\u0649\u0655\u0650\u0642\u064f\u0648\u0652\u0646\u064e ","transliteration":{"en":"Fahaqqa 'alainaa qawlu Rabbinaaa innaa lazaaa'iqoon","id":"Fa \u1e25aqqa \u2018alain\u0101 qaulu rabbin\u0101, inn\u0101 la\u017c\u0101'iq\u016bn(a)."}},"translation":{"en":"So the word of our Lord has come into effect upon us; indeed, we will taste [punishment].","id":"Maka pastilah putusan (azab) Tuhan kita menimpa atas kita; sesungguhnya kita akan merasakan (azab itu)."},"audio":{"primary":"https:\/\/cdn.islamic.network\/quran\/audio\/128\/ar.alafasy\/3819.mp3","secondary":["https:\/\/cdn.islamic.network\/quran\/audio\/64\/ar.alafasy\/3819.mp3"]},"tafsir":{"id":{"short":"-","long":"-"}}},{"number":{"inQuran":3820,"inSurah":32},"meta":{"juz":23,"page":447,"manzil":6,"ruku":387,"hizbQuarter":179,"sajda":{"recommended":false,"obligatory":false}},"surah":{"number":37,"sequence":56,"numberOfVerses":182,"name":{"short":"\u0627\u0644\u0635\u0627\u0641\u0627\u062a","long":"\u0627\u0644\u0635\u0627\u0641\u0627\u062a","transliteration":{"en":"As-Saffat","id":"As-Saffat"},"translation":{"en":"Those who set the Ranks","id":"Barisan-barisan"}},"bismillah_pre":true,"preBismillah":{"preBismillah":{"text":{"arab":"\u0628\u0650\u0633\u0652\u0645\u0650 \u0627\u0644\u0644\u0651\u064e\u0647\u0650 \u0627\u0644\u0631\u0651\u064e\u062d\u0652\u0645\u064e\u0670\u0646\u0650 \u0627\u0644\u0631\u0651\u064e\u062d\u0650\u064a\u0645\u0650","transliteration":{"en":"Bismillaahir Rahmaanir Raheem"}},"translation":{"en":"In the name of Allah, the Entirely Merciful, the Especially Merciful.","id":"Dengan nama Allah Yang Maha Pengasih, Maha Penyayang."},"audio":{"primary":"https:\/\/cdn.alquran.cloud\/media\/audio\/ayah\/ar.alafasy\/1","secondary":["https:\/\/cdn.islamic.network\/quran\/audio\/128\/ar.alafasy\/1.mp3","https:\/\/cdn.islamic.network\/quran\/audio\/64\/ar.alafasy\/1.mp3"]}}},"relevation":{"arab":"\u0645\u0643\u0629","en":"Meccan","id":"Makkiyyah"},"tafsir":{"en":"TBD","id":"TBD"}},"text":{"arab":"\u0641\u064e\u0627\u064e\u063a\u0652\u0648\u064e\u064a\u0652\u0646\u0670\u0643\u064f\u0645\u0652 \u0627\u0650\u0646\u0651\u064e\u0627 \u0643\u064f\u0646\u0651\u064e\u0627 \u063a\u0670\u0648\u0650\u064a\u0652\u0646\u064e ","transliteration":{"en":"Fa aghwainaakum innaa kunnaa ghaaween","id":"Fa agwain\u0101kum inn\u0101 kunn\u0101 g\u0101w\u012bn(a)."}},"translation":{"en":"And we led you to deviation; indeed, we were deviators.\"","id":"Maka kami telah menyesatkan kamu, sesungguhnya kami adalah orang-orang yang sesat."},"audio":{"primary":"https:\/\/cdn.islamic.network\/quran\/audio\/128\/ar.alafasy\/3820.mp3","secondary":["https:\/\/cdn.islamic.network\/quran\/audio\/64\/ar.alafasy\/3820.mp3"]},"tafsir":{"id":{"short":"-","long":"-"}}},{"number":{"inQuran":3821,"inSurah":33},"meta":{"juz":23,"page":447,"manzil":6,"ruku":387,"hizbQuarter":179,"sajda":{"recommended":false,"obligatory":false}},"surah":{"number":37,"sequence":56,"numberOfVerses":182,"name":{"short":"\u0627\u0644\u0635\u0627\u0641\u0627\u062a","long":"\u0627\u0644\u0635\u0627\u0641\u0627\u062a","transliteration":{"en":"As-Saffat","id":"As-Saffat"},"translation":{"en":"Those who set the Ranks","id":"Barisan-barisan"}},"bismillah_pre":true,"preBismillah":{"preBismillah":{"text":{"arab":"\u0628\u0650\u0633\u0652\u0645\u0650 \u0627\u0644\u0644\u0651\u064e\u0647\u0650 \u0627\u0644\u0631\u0651\u064e\u062d\u0652\u0645\u064e\u0670\u0646\u0650 \u0627\u0644\u0631\u0651\u064e\u062d\u0650\u064a\u0645\u0650","transliteration":{"en":"Bismillaahir Rahmaanir Raheem"}},"translation":{"en":"In the name of Allah, the Entirely Merciful, the Especially Merciful.","id":"Dengan nama Allah Yang Maha Pengasih, Maha Penyayang."},"audio":{"primary":"https:\/\/cdn.alquran.cloud\/media\/audio\/ayah\/ar.alafasy\/1","secondary":["https:\/\/cdn.islamic.network\/quran\/audio\/128\/ar.alafasy\/1.mp3","https:\/\/cdn.islamic.network\/quran\/audio\/64\/ar.alafasy\/1.mp3"]}}},"relevation":{"arab":"\u0645\u0643\u0629","en":"Meccan","id":"Makkiyyah"},"tafsir":{"en":"TBD","id":"TBD"}},"text":{"arab":"\u0641\u064e\u0627\u0650\u0646\u0651\u064e\u0647\u064f\u0645\u0652 \u064a\u064e\u0648\u0652\u0645\u064e\u0649\u0655\u0650\u0630\u064d \u0641\u0650\u0649 \u0627\u0644\u0652\u0639\u064e\u0630\u064e\u0627\u0628\u0650 \u0645\u064f\u0634\u0652\u062a\u064e\u0631\u0650\u0643\u064f\u0648\u0652\u0646\u064e","transliteration":{"en":"Fa innahum Yawma'izin fil'azaabi mushtarikoon","id":"Fa innahum yauma'i\u017cin fil-\u2018a\u017c\u0101bi musytarik\u016bn(a)."}},"translation":{"en":"So indeed they, that Day, will be sharing in the punishment.","id":"Maka sesungguhnya mereka pada hari itu bersama-sama dalam azab."},"audio":{"primary":"https:\/\/cdn.islamic.network\/quran\/audio\/128\/ar.alafasy\/3821.mp3","secondary":["https:\/\/cdn.islamic.network\/quran\/audio\/64\/ar.alafasy\/3821.mp3"]},"tafsir":{"id":{"short":"-","long":"-"}}},{"number":{"inQuran":3822,"inSurah":34},"meta":{"juz":23,"page":447,"manzil":6,"ruku":387,"hizbQuarter":179,"sajda":{"recommended":false,"obligatory":false}},"surah":{"number":37,"sequence":56,"numberOfVerses":182,"name":{"short":"\u0627\u0644\u0635\u0627\u0641\u0627\u062a","long":"\u0627\u0644\u0635\u0627\u0641\u0627\u062a","transliteration":{"en":"As-Saffat","id":"As-Saffat"},"translation":{"en":"Those who set the Ranks","id":"Barisan-barisan"}},"bismillah_pre":true,"preBismillah":{"preBismillah":{"text":{"arab":"\u0628\u0650\u0633\u0652\u0645\u0650 \u0627\u0644\u0644\u0651\u064e\u0647\u0650 \u0627\u0644\u0631\u0651\u064e\u062d\u0652\u0645\u064e\u0670\u0646\u0650 \u0627\u0644\u0631\u0651\u064e\u062d\u0650\u064a\u0645\u0650","transliteration":{"en":"Bismillaahir Rahmaanir Raheem"}},"translation":{"en":"In the name of Allah, the Entirely Merciful, the Especially Merciful.","id":"Dengan nama Allah Yang Maha Pengasih, Maha Penyayang."},"audio":{"primary":"https:\/\/cdn.alquran.cloud\/media\/audio\/ayah\/ar.alafasy\/1","secondary":["https:\/\/cdn.islamic.network\/quran\/audio\/128\/ar.alafasy\/1.mp3","https:\/\/cdn.islamic.network\/quran\/audio\/64\/ar.alafasy\/1.mp3"]}}},"relevation":{"arab":"\u0645\u0643\u0629","en":"Meccan","id":"Makkiyyah"},"tafsir":{"en":"TBD","id":"TBD"}},"text":{"arab":"\u0627\u0650\u0646\u0651\u064e\u0627 \u0643\u064e\u0630\u0670\u0644\u0650\u0643\u064e \u0646\u064e\u0641\u0652\u0639\u064e\u0644\u064f \u0628\u0650\u0627\u0644\u0652\u0645\u064f\u062c\u0652\u0631\u0650\u0645\u0650\u064a\u0652\u0646\u064e","transliteration":{"en":"Innaa kazaalika naf'alu bil mujrimeen","id":"Inn\u0101 ka\u017c\u0101lika naf\u2018alu bil-mujrim\u012bn(a)."}},"translation":{"en":"Indeed, that is how We deal with the criminals.","id":"Sesungguhnya demikianlah Kami berbuat terhadap orang-orang yang berbuat jahat."},"audio":{"primary":"https:\/\/cdn.islamic.network\/quran\/audio\/128\/ar.alafasy\/3822.mp3","secondary":["https:\/\/cdn.islamic.network\/quran\/audio\/64\/ar.alafasy\/3822.mp3"]},"tafsir":{"id":{"short":"-","long":"-"}}},{"number":{"inQuran":3823,"inSurah":35},"meta":{"juz":23,"page":447,"manzil":6,"ruku":387,"hizbQuarter":179,"sajda":{"recommended":false,"obligatory":false}},"surah":{"number":37,"sequence":56,"numberOfVerses":182,"name":{"short":"\u0627\u0644\u0635\u0627\u0641\u0627\u062a","long":"\u0627\u0644\u0635\u0627\u0641\u0627\u062a","transliteration":{"en":"As-Saffat","id":"As-Saffat"},"translation":{"en":"Those who set the Ranks","id":"Barisan-barisan"}},"bismillah_pre":true,"preBismillah":{"preBismillah":{"text":{"arab":"\u0628\u0650\u0633\u0652\u0645\u0650 \u0627\u0644\u0644\u0651\u064e\u0647\u0650 \u0627\u0644\u0631\u0651\u064e\u062d\u0652\u0645\u064e\u0670\u0646\u0650 \u0627\u0644\u0631\u0651\u064e\u062d\u0650\u064a\u0645\u0650","transliteration":{"en":"Bismillaahir Rahmaanir Raheem"}},"translation":{"en":"In the name of Allah, the Entirely Merciful, the Especially Merciful.","id":"Dengan nama Allah Yang Maha Pengasih, Maha Penyayang."},"audio":{"primary":"https:\/\/cdn.alquran.cloud\/media\/audio\/ayah\/ar.alafasy\/1","secondary":["https:\/\/cdn.islamic.network\/quran\/audio\/128\/ar.alafasy\/1.mp3","https:\/\/cdn.islamic.network\/quran\/audio\/64\/ar.alafasy\/1.mp3"]}}},"relevation":{"arab":"\u0645\u0643\u0629","en":"Meccan","id":"Makkiyyah"},"tafsir":{"en":"TBD","id":"TBD"}},"text":{"arab":"\u0627\u0650\u0646\u0651\u064e\u0647\u064f\u0645\u0652 \u0643\u064e\u0627\u0646\u064f\u0648\u0652\u0653\u0627 \u0627\u0650\u0630\u064e\u0627 \u0642\u0650\u064a\u0652\u0644\u064e \u0644\u064e\u0647\u064f\u0645\u0652 \u0644\u064e\u0627\u0653 \u0627\u0650\u0644\u0670\u0647\u064e \u0627\u0650\u0644\u0651\u064e\u0627 \u0627\u0644\u0644\u0651\u0670\u0647\u064f \u064a\u064e\u0633\u0652\u062a\u064e\u0643\u0652\u0628\u0650\u0631\u064f\u0648\u0652\u0646\u064e \u06d9","transliteration":{"en":"Innahum kaanooo izaa qeela lahum laaa ilaaha illal laahu yastakbiroon","id":"Innahum k\u0101n\u016b i\u017c\u0101 q\u012bla lahum l\u0101 il\u0101ha illall\u0101hu yastakbir\u016bn(a)."}},"translation":{"en":"Indeed they, when it was said to them, \"There is no deity but Allah,\" were arrogant","id":"Sesungguhnya mereka dahulu apabila dikatakan kepada mereka: \"Laa ilaaha illallah\" (Tiada Tuhan yang berhak disembah melainkan Allah) mereka menyombongkan diri,"},"audio":{"primary":"https:\/\/cdn.islamic.network\/quran\/audio\/128\/ar.alafasy\/3823.mp3","secondary":["https:\/\/cdn.islamic.network\/quran\/audio\/64\/ar.alafasy\/3823.mp3"]},"tafsir":{"id":{"short":"-","long":"-"}}},{"number":{"inQuran":3824,"inSurah":36},"meta":{"juz":23,"page":447,"manzil":6,"ruku":387,"hizbQuarter":179,"sajda":{"recommended":false,"obligatory":false}},"surah":{"number":37,"sequence":56,"numberOfVerses":182,"name":{"short":"\u0627\u0644\u0635\u0627\u0641\u0627\u062a","long":"\u0627\u0644\u0635\u0627\u0641\u0627\u062a","transliteration":{"en":"As-Saffat","id":"As-Saffat"},"translation":{"en":"Those who set the Ranks","id":"Barisan-barisan"}},"bismillah_pre":true,"preBismillah":{"preBismillah":{"text":{"arab":"\u0628\u0650\u0633\u0652\u0645\u0650 \u0627\u0644\u0644\u0651\u064e\u0647\u0650 \u0627\u0644\u0631\u0651\u064e\u062d\u0652\u0645\u064e\u0670\u0646\u0650 \u0627\u0644\u0631\u0651\u064e\u062d\u0650\u064a\u0645\u0650","transliteration":{"en":"Bismillaahir Rahmaanir Raheem"}},"translation":{"en":"In the name of Allah, the Entirely Merciful, the Especially Merciful.","id":"Dengan nama Allah Yang Maha Pengasih, Maha Penyayang."},"audio":{"primary":"https:\/\/cdn.alquran.cloud\/media\/audio\/ayah\/ar.alafasy\/1","secondary":["https:\/\/cdn.islamic.network\/quran\/audio\/128\/ar.alafasy\/1.mp3","https:\/\/cdn.islamic.network\/quran\/audio\/64\/ar.alafasy\/1.mp3"]}}},"relevation":{"arab":"\u0645\u0643\u0629","en":"Meccan","id":"Makkiyyah"},"tafsir":{"en":"TBD","id":"TBD"}},"text":{"arab":"\u0648\u064e\u064a\u064e\u0642\u064f\u0648\u0652\u0644\u064f\u0648\u0652\u0646\u064e \u0627\u064e\u0649\u0655\u0650\u0646\u0651\u064e\u0627 \u0644\u064e\u062a\u064e\u0627\u0631\u0650\u0643\u064f\u0648\u0652\u0653\u0627 \u0627\u0670\u0644\u0650\u0647\u064e\u062a\u0650\u0646\u064e\u0627 \u0644\u0650\u0634\u064e\u0627\u0639\u0650\u0631\u064d \u0645\u0651\u064e\u062c\u0652\u0646\u064f\u0648\u0652\u0646\u064d \u06d7 ","transliteration":{"en":"Wa yaqooloona a'innaa lataarikooo aalihatinaa lishaa'irim majnoon","id":"Wa yaq\u016bl\u016bna a'inn\u0101 lat\u0101rik\u016b \u0101lihatin\u0101 lisy\u0101\u2018irim majn\u016bn(in)."}},"translation":{"en":"And were saying, \"Are we to leave our gods for a mad poet?\"","id":"dan mereka berkata: \"Apakah sesungguhnya kami harus meninggalkan sembahan-sembahan kami karena seorang penyair gila?\""},"audio":{"primary":"https:\/\/cdn.islamic.network\/quran\/audio\/128\/ar.alafasy\/3824.mp3","secondary":["https:\/\/cdn.islamic.network\/quran\/audio\/64\/ar.alafasy\/3824.mp3"]},"tafsir":{"id":{"short":"-","long":"-"}}},{"number":{"inQuran":3825,"inSurah":37},"meta":{"juz":23,"page":447,"manzil":6,"ruku":387,"hizbQuarter":179,"sajda":{"recommended":false,"obligatory":false}},"surah":{"number":37,"sequence":56,"numberOfVerses":182,"name":{"short":"\u0627\u0644\u0635\u0627\u0641\u0627\u062a","long":"\u0627\u0644\u0635\u0627\u0641\u0627\u062a","transliteration":{"en":"As-Saffat","id":"As-Saffat"},"translation":{"en":"Those who set the Ranks","id":"Barisan-barisan"}},"bismillah_pre":true,"preBismillah":{"preBismillah":{"text":{"arab":"\u0628\u0650\u0633\u0652\u0645\u0650 \u0627\u0644\u0644\u0651\u064e\u0647\u0650 \u0627\u0644\u0631\u0651\u064e\u062d\u0652\u0645\u064e\u0670\u0646\u0650 \u0627\u0644\u0631\u0651\u064e\u062d\u0650\u064a\u0645\u0650","transliteration":{"en":"Bismillaahir Rahmaanir Raheem"}},"translation":{"en":"In the name of Allah, the Entirely Merciful, the Especially Merciful.","id":"Dengan nama Allah Yang Maha Pengasih, Maha Penyayang."},"audio":{"primary":"https:\/\/cdn.alquran.cloud\/media\/audio\/ayah\/ar.alafasy\/1","secondary":["https:\/\/cdn.islamic.network\/quran\/audio\/128\/ar.alafasy\/1.mp3","https:\/\/cdn.islamic.network\/quran\/audio\/64\/ar.alafasy\/1.mp3"]}}},"relevation":{"arab":"\u0645\u0643\u0629","en":"Meccan","id":"Makkiyyah"},"tafsir":{"en":"TBD","id":"TBD"}},"text":{"arab":"\u0628\u064e\u0644\u0652 \u062c\u064e\u0627\u06e4\u0621\u064e \u0628\u0650\u0627\u0644\u0652\u062d\u064e\u0642\u0651\u0650 \u0648\u064e\u0635\u064e\u062f\u0651\u064e\u0642\u064e \u0627\u0644\u0652\u0645\u064f\u0631\u0652\u0633\u064e\u0644\u0650\u064a\u0652\u0646\u064e","transliteration":{"en":"bal jaaa'a bilhaqqi wa saddaqal mursaleen","id":"Bal j\u0101'a bil-\u1e25aqqi wa \u1e63addaqal-mursal\u012bn(a)."}},"translation":{"en":"Rather, the Prophet has come with the truth and confirmed the [previous] messengers.","id":"Sebenarnya dia (Muhammad) telah datang membawa kebenaran dan membenarkan rasul-rasul (sebelumnya)."},"audio":{"primary":"https:\/\/cdn.islamic.network\/quran\/audio\/128\/ar.alafasy\/3825.mp3","secondary":["https:\/\/cdn.islamic.network\/quran\/audio\/64\/ar.alafasy\/3825.mp3"]},"tafsir":{"id":{"short":"-","long":"-"}}},{"number":{"inQuran":3826,"inSurah":38},"meta":{"juz":23,"page":447,"manzil":6,"ruku":387,"hizbQuarter":179,"sajda":{"recommended":false,"obligatory":false}},"surah":{"number":37,"sequence":56,"numberOfVerses":182,"name":{"short":"\u0627\u0644\u0635\u0627\u0641\u0627\u062a","long":"\u0627\u0644\u0635\u0627\u0641\u0627\u062a","transliteration":{"en":"As-Saffat","id":"As-Saffat"},"translation":{"en":"Those who set the Ranks","id":"Barisan-barisan"}},"bismillah_pre":true,"preBismillah":{"preBismillah":{"text":{"arab":"\u0628\u0650\u0633\u0652\u0645\u0650 \u0627\u0644\u0644\u0651\u064e\u0647\u0650 \u0627\u0644\u0631\u0651\u064e\u062d\u0652\u0645\u064e\u0670\u0646\u0650 \u0627\u0644\u0631\u0651\u064e\u062d\u0650\u064a\u0645\u0650","transliteration":{"en":"Bismillaahir Rahmaanir Raheem"}},"translation":{"en":"In the name of Allah, the Entirely Merciful, the Especially Merciful.","id":"Dengan nama Allah Yang Maha Pengasih, Maha Penyayang."},"audio":{"primary":"https:\/\/cdn.alquran.cloud\/media\/audio\/ayah\/ar.alafasy\/1","secondary":["https:\/\/cdn.islamic.network\/quran\/audio\/128\/ar.alafasy\/1.mp3","https:\/\/cdn.islamic.network\/quran\/audio\/64\/ar.alafasy\/1.mp3"]}}},"relevation":{"arab":"\u0645\u0643\u0629","en":"Meccan","id":"Makkiyyah"},"tafsir":{"en":"TBD","id":"TBD"}},"text":{"arab":"\u0627\u0650\u0646\u0651\u064e\u0643\u064f\u0645\u0652 \u0644\u064e\u0630\u064e\u0627\u06e4\u0649\u0655\u0650\u0642\u064f\u0648\u0627 \u0627\u0644\u0652\u0639\u064e\u0630\u064e\u0627\u0628\u0650 \u0627\u0644\u0652\u0627\u064e\u0644\u0650\u064a\u0652\u0645\u0650 \u06da ","transliteration":{"en":"Innakum lazaaa'iqul 'azaabil aleem","id":"Innakum la\u017c\u0101'iqul-\u2018a\u017c\u0101bil-al\u012bm(i)."}},"translation":{"en":"Indeed, you [disbelievers] will be tasters of the painful punishment,","id":"Sesungguhnya kamu pasti akan merasakan azab yang pedih."},"audio":{"primary":"https:\/\/cdn.islamic.network\/quran\/audio\/128\/ar.alafasy\/3826.mp3","secondary":["https:\/\/cdn.islamic.network\/quran\/audio\/64\/ar.alafasy\/3826.mp3"]},"tafsir":{"id":{"short":"-","long":"-"}}},{"number":{"inQuran":3827,"inSurah":39},"meta":{"juz":23,"page":447,"manzil":6,"ruku":387,"hizbQuarter":179,"sajda":{"recommended":false,"obligatory":false}},"surah":{"number":37,"sequence":56,"numberOfVerses":182,"name":{"short":"\u0627\u0644\u0635\u0627\u0641\u0627\u062a","long":"\u0627\u0644\u0635\u0627\u0641\u0627\u062a","transliteration":{"en":"As-Saffat","id":"As-Saffat"},"translation":{"en":"Those who set the Ranks","id":"Barisan-barisan"}},"bismillah_pre":true,"preBismillah":{"preBismillah":{"text":{"arab":"\u0628\u0650\u0633\u0652\u0645\u0650 \u0627\u0644\u0644\u0651\u064e\u0647\u0650 \u0627\u0644\u0631\u0651\u064e\u062d\u0652\u0645\u064e\u0670\u0646\u0650 \u0627\u0644\u0631\u0651\u064e\u062d\u0650\u064a\u0645\u0650","transliteration":{"en":"Bismillaahir Rahmaanir Raheem"}},"translation":{"en":"In the name of Allah, the Entirely Merciful, the Especially Merciful.","id":"Dengan nama Allah Yang Maha Pengasih, Maha Penyayang."},"audio":{"primary":"https:\/\/cdn.alquran.cloud\/media\/audio\/ayah\/ar.alafasy\/1","secondary":["https:\/\/cdn.islamic.network\/quran\/audio\/128\/ar.alafasy\/1.mp3","https:\/\/cdn.islamic.network\/quran\/audio\/64\/ar.alafasy\/1.mp3"]}}},"relevation":{"arab":"\u0645\u0643\u0629","en":"Meccan","id":"Makkiyyah"},"tafsir":{"en":"TBD","id":"TBD"}},"text":{"arab":"\u0648\u064e\u0645\u064e\u0627 \u062a\u064f\u062c\u0652\u0632\u064e\u0648\u0652\u0646\u064e \u0627\u0650\u0644\u0651\u064e\u0627 \u0645\u064e\u0627 \u0643\u064f\u0646\u0652\u062a\u064f\u0645\u0652 \u062a\u064e\u0639\u0652\u0645\u064e\u0644\u064f\u0648\u0652\u0646\u064e\u06d9","transliteration":{"en":"Wa maa tujzawna illaa maa kuntum ta'maloon","id":"Wa m\u0101 tujzauna ill\u0101 m\u0101 kuntum ta\u2018mal\u016bn(a)."}},"translation":{"en":"And you will not be recompensed except for what you used to do -","id":"Dan kamu tidak diberi pembalasan melainkan terhadap kejahatan yang telah kamu kerjakan,"},"audio":{"primary":"https:\/\/cdn.islamic.network\/quran\/audio\/128\/ar.alafasy\/3827.mp3","secondary":["https:\/\/cdn.islamic.network\/quran\/audio\/64\/ar.alafasy\/3827.mp3"]},"tafsir":{"id":{"short":"-","long":"-"}}},{"number":{"inQuran":3828,"inSurah":40},"meta":{"juz":23,"page":447,"manzil":6,"ruku":387,"hizbQuarter":179,"sajda":{"recommended":false,"obligatory":false}},"surah":{"number":37,"sequence":56,"numberOfVerses":182,"name":{"short":"\u0627\u0644\u0635\u0627\u0641\u0627\u062a","long":"\u0627\u0644\u0635\u0627\u0641\u0627\u062a","transliteration":{"en":"As-Saffat","id":"As-Saffat"},"translation":{"en":"Those who set the Ranks","id":"Barisan-barisan"}},"bismillah_pre":true,"preBismillah":{"preBismillah":{"text":{"arab":"\u0628\u0650\u0633\u0652\u0645\u0650 \u0627\u0644\u0644\u0651\u064e\u0647\u0650 \u0627\u0644\u0631\u0651\u064e\u062d\u0652\u0645\u064e\u0670\u0646\u0650 \u0627\u0644\u0631\u0651\u064e\u062d\u0650\u064a\u0645\u0650","transliteration":{"en":"Bismillaahir Rahmaanir Raheem"}},"translation":{"en":"In the name of Allah, the Entirely Merciful, the Especially Merciful.","id":"Dengan nama Allah Yang Maha Pengasih, Maha Penyayang."},"audio":{"primary":"https:\/\/cdn.alquran.cloud\/media\/audio\/ayah\/ar.alafasy\/1","secondary":["https:\/\/cdn.islamic.network\/quran\/audio\/128\/ar.alafasy\/1.mp3","https:\/\/cdn.islamic.network\/quran\/audio\/64\/ar.alafasy\/1.mp3"]}}},"relevation":{"arab":"\u0645\u0643\u0629","en":"Meccan","id":"Makkiyyah"},"tafsir":{"en":"TBD","id":"TBD"}},"text":{"arab":"\u0627\u0650\u0644\u0651\u064e\u0627 \u0639\u0650\u0628\u064e\u0627\u062f\u064e \u0627\u0644\u0644\u0651\u0670\u0647\u0650 \u0627\u0644\u0652\u0645\u064f\u062e\u0652\u0644\u064e\u0635\u0650\u064a\u0652\u0646\u064e ","transliteration":{"en":"Illaa 'ibaadal laahil mukhlaseen","id":"Ill\u0101 \u2018ib\u0101dall\u0101hil-mukhla\u1e63\u012bn(a)."}},"translation":{"en":"But not the chosen servants of Allah.","id":"tetapi hamba-hamba Allah yang dibersihkan (dari dosa)."},"audio":{"primary":"https:\/\/cdn.islamic.network\/quran\/audio\/128\/ar.alafasy\/3828.mp3","secondary":["https:\/\/cdn.islamic.network\/quran\/audio\/64\/ar.alafasy\/3828.mp3"]},"tafsir":{"id":{"short":"-","long":"-"}}},{"number":{"inQuran":3829,"inSurah":41},"meta":{"juz":23,"page":447,"manzil":6,"ruku":387,"hizbQuarter":179,"sajda":{"recommended":false,"obligatory":false}},"surah":{"number":37,"sequence":56,"numberOfVerses":182,"name":{"short":"\u0627\u0644\u0635\u0627\u0641\u0627\u062a","long":"\u0627\u0644\u0635\u0627\u0641\u0627\u062a","transliteration":{"en":"As-Saffat","id":"As-Saffat"},"translation":{"en":"Those who set the Ranks","id":"Barisan-barisan"}},"bismillah_pre":true,"preBismillah":{"preBismillah":{"text":{"arab":"\u0628\u0650\u0633\u0652\u0645\u0650 \u0627\u0644\u0644\u0651\u064e\u0647\u0650 \u0627\u0644\u0631\u0651\u064e\u062d\u0652\u0645\u064e\u0670\u0646\u0650 \u0627\u0644\u0631\u0651\u064e\u062d\u0650\u064a\u0645\u0650","transliteration":{"en":"Bismillaahir Rahmaanir Raheem"}},"translation":{"en":"In the name of Allah, the Entirely Merciful, the Especially Merciful.","id":"Dengan nama Allah Yang Maha Pengasih, Maha Penyayang."},"audio":{"primary":"https:\/\/cdn.alquran.cloud\/media\/audio\/ayah\/ar.alafasy\/1","secondary":["https:\/\/cdn.islamic.network\/quran\/audio\/128\/ar.alafasy\/1.mp3","https:\/\/cdn.islamic.network\/quran\/audio\/64\/ar.alafasy\/1.mp3"]}}},"relevation":{"arab":"\u0645\u0643\u0629","en":"Meccan","id":"Makkiyyah"},"tafsir":{"en":"TBD","id":"TBD"}},"text":{"arab":"\u0627\u064f\u0648\u0644\u0670\u06e4\u0649\u0655\u0650\u0643\u064e \u0644\u064e\u0647\u064f\u0645\u0652 \u0631\u0650\u0632\u0652\u0642\u064c \u0645\u0651\u064e\u0639\u0652\u0644\u064f\u0648\u0652\u0645\u064c\u06d9","transliteration":{"en":"Ulaaa'ika lahum rizqum ma'loom","id":"Ul\u0101'ika lahum rizqum ma\u2018l\u016bm(un)."}},"translation":{"en":"Those will have a provision determined -","id":"Mereka itu memperoleh rezeki yang tertentu,"},"audio":{"primary":"https:\/\/cdn.islamic.network\/quran\/audio\/128\/ar.alafasy\/3829.mp3","secondary":["https:\/\/cdn.islamic.network\/quran\/audio\/64\/ar.alafasy\/3829.mp3"]},"tafsir":{"id":{"short":"-","long":"-"}}},{"number":{"inQuran":3830,"inSurah":42},"meta":{"juz":23,"page":447,"manzil":6,"ruku":387,"hizbQuarter":179,"sajda":{"recommended":false,"obligatory":false}},"surah":{"number":37,"sequence":56,"numberOfVerses":182,"name":{"short":"\u0627\u0644\u0635\u0627\u0641\u0627\u062a","long":"\u0627\u0644\u0635\u0627\u0641\u0627\u062a","transliteration":{"en":"As-Saffat","id":"As-Saffat"},"translation":{"en":"Those who set the Ranks","id":"Barisan-barisan"}},"bismillah_pre":true,"preBismillah":{"preBismillah":{"text":{"arab":"\u0628\u0650\u0633\u0652\u0645\u0650 \u0627\u0644\u0644\u0651\u064e\u0647\u0650 \u0627\u0644\u0631\u0651\u064e\u062d\u0652\u0645\u064e\u0670\u0646\u0650 \u0627\u0644\u0631\u0651\u064e\u062d\u0650\u064a\u0645\u0650","transliteration":{"en":"Bismillaahir Rahmaanir Raheem"}},"translation":{"en":"In the name of Allah, the Entirely Merciful, the Especially Merciful.","id":"Dengan nama Allah Yang Maha Pengasih, Maha Penyayang."},"audio":{"primary":"https:\/\/cdn.alquran.cloud\/media\/audio\/ayah\/ar.alafasy\/1","secondary":["https:\/\/cdn.islamic.network\/quran\/audio\/128\/ar.alafasy\/1.mp3","https:\/\/cdn.islamic.network\/quran\/audio\/64\/ar.alafasy\/1.mp3"]}}},"relevation":{"arab":"\u0645\u0643\u0629","en":"Meccan","id":"Makkiyyah"},"tafsir":{"en":"TBD","id":"TBD"}},"text":{"arab":"\u0641\u064e\u0648\u064e\u0627\u0643\u0650\u0647\u064f \u06da\u0648\u064e\u0647\u064f\u0645\u0652 \u0645\u0651\u064f\u0643\u0652\u0631\u064e\u0645\u064f\u0648\u0652\u0646\u064e\u06d9","transliteration":{"en":"Fa waakihu wa hum mukramoon","id":"Faw\u0101kihu wa hum mukram\u016bn(a)."}},"translation":{"en":"Fruits; and they will be honored","id":"yaitu buah-buahan. Dan mereka adalah orang-orang yang dimuliakan,"},"audio":{"primary":"https:\/\/cdn.islamic.network\/quran\/audio\/128\/ar.alafasy\/3830.mp3","secondary":["https:\/\/cdn.islamic.network\/quran\/audio\/64\/ar.alafasy\/3830.mp3"]},"tafsir":{"id":{"short":"-","long":"-"}}},{"number":{"inQuran":3831,"inSurah":43},"meta":{"juz":23,"page":447,"manzil":6,"ruku":387,"hizbQuarter":179,"sajda":{"recommended":false,"obligatory":false}},"surah":{"number":37,"sequence":56,"numberOfVerses":182,"name":{"short":"\u0627\u0644\u0635\u0627\u0641\u0627\u062a","long":"\u0627\u0644\u0635\u0627\u0641\u0627\u062a","transliteration":{"en":"As-Saffat","id":"As-Saffat"},"translation":{"en":"Those who set the Ranks","id":"Barisan-barisan"}},"bismillah_pre":true,"preBismillah":{"preBismillah":{"text":{"arab":"\u0628\u0650\u0633\u0652\u0645\u0650 \u0627\u0644\u0644\u0651\u064e\u0647\u0650 \u0627\u0644\u0631\u0651\u064e\u062d\u0652\u0645\u064e\u0670\u0646\u0650 \u0627\u0644\u0631\u0651\u064e\u062d\u0650\u064a\u0645\u0650","transliteration":{"en":"Bismillaahir Rahmaanir Raheem"}},"translation":{"en":"In the name of Allah, the Entirely Merciful, the Especially Merciful.","id":"Dengan nama Allah Yang Maha Pengasih, Maha Penyayang."},"audio":{"primary":"https:\/\/cdn.alquran.cloud\/media\/audio\/ayah\/ar.alafasy\/1","secondary":["https:\/\/cdn.islamic.network\/quran\/audio\/128\/ar.alafasy\/1.mp3","https:\/\/cdn.islamic.network\/quran\/audio\/64\/ar.alafasy\/1.mp3"]}}},"relevation":{"arab":"\u0645\u0643\u0629","en":"Meccan","id":"Makkiyyah"},"tafsir":{"en":"TBD","id":"TBD"}},"text":{"arab":"\u0641\u0650\u064a\u0652 \u062c\u064e\u0646\u0651\u0670\u062a\u0650 \u0627\u0644\u0646\u0651\u064e\u0639\u0650\u064a\u0652\u0645\u0650\u06d9","transliteration":{"en":"Fee jannaatin Na'eem","id":"F\u012b jann\u0101tin na\u2018\u012bm(i)."}},"translation":{"en":"In gardens of pleasure","id":"di dalam surga-surga yang penuh nikmat."},"audio":{"primary":"https:\/\/cdn.islamic.network\/quran\/audio\/128\/ar.alafasy\/3831.mp3","secondary":["https:\/\/cdn.islamic.network\/quran\/audio\/64\/ar.alafasy\/3831.mp3"]},"tafsir":{"id":{"short":"-","long":"-"}}},{"number":{"inQuran":3832,"inSurah":44},"meta":{"juz":23,"page":447,"manzil":6,"ruku":387,"hizbQuarter":179,"sajda":{"recommended":false,"obligatory":false}},"surah":{"number":37,"sequence":56,"numberOfVerses":182,"name":{"short":"\u0627\u0644\u0635\u0627\u0641\u0627\u062a","long":"\u0627\u0644\u0635\u0627\u0641\u0627\u062a","transliteration":{"en":"As-Saffat","id":"As-Saffat"},"translation":{"en":"Those who set the Ranks","id":"Barisan-barisan"}},"bismillah_pre":true,"preBismillah":{"preBismillah":{"text":{"arab":"\u0628\u0650\u0633\u0652\u0645\u0650 \u0627\u0644\u0644\u0651\u064e\u0647\u0650 \u0627\u0644\u0631\u0651\u064e\u062d\u0652\u0645\u064e\u0670\u0646\u0650 \u0627\u0644\u0631\u0651\u064e\u062d\u0650\u064a\u0645\u0650","transliteration":{"en":"Bismillaahir Rahmaanir Raheem"}},"translation":{"en":"In the name of Allah, the Entirely Merciful, the Especially Merciful.","id":"Dengan nama Allah Yang Maha Pengasih, Maha Penyayang."},"audio":{"primary":"https:\/\/cdn.alquran.cloud\/media\/audio\/ayah\/ar.alafasy\/1","secondary":["https:\/\/cdn.islamic.network\/quran\/audio\/128\/ar.alafasy\/1.mp3","https:\/\/cdn.islamic.network\/quran\/audio\/64\/ar.alafasy\/1.mp3"]}}},"relevation":{"arab":"\u0645\u0643\u0629","en":"Meccan","id":"Makkiyyah"},"tafsir":{"en":"TBD","id":"TBD"}},"text":{"arab":"\u0639\u064e\u0644\u0670\u0649 \u0633\u064f\u0631\u064f\u0631\u064d \u0645\u0651\u064f\u062a\u064e\u0642\u0670\u0628\u0650\u0644\u0650\u064a\u0652\u0646\u064e","transliteration":{"en":"'Alaa sururim mutaqaa bileen","id":"\u2018Al\u0101 sururim mutaq\u0101bil\u012bn(a)."}},"translation":{"en":"On thrones facing one another.","id":"di atas takhta-takhta kebesaran berhadap-hadapan."},"audio":{"primary":"https:\/\/cdn.islamic.network\/quran\/audio\/128\/ar.alafasy\/3832.mp3","secondary":["https:\/\/cdn.islamic.network\/quran\/audio\/64\/ar.alafasy\/3832.mp3"]},"tafsir":{"id":{"short":"-","long":"-"}}},{"number":{"inQuran":3833,"inSurah":45},"meta":{"juz":23,"page":447,"manzil":6,"ruku":387,"hizbQuarter":179,"sajda":{"recommended":false,"obligatory":false}},"surah":{"number":37,"sequence":56,"numberOfVerses":182,"name":{"short":"\u0627\u0644\u0635\u0627\u0641\u0627\u062a","long":"\u0627\u0644\u0635\u0627\u0641\u0627\u062a","transliteration":{"en":"As-Saffat","id":"As-Saffat"},"translation":{"en":"Those who set the Ranks","id":"Barisan-barisan"}},"bismillah_pre":true,"preBismillah":{"preBismillah":{"text":{"arab":"\u0628\u0650\u0633\u0652\u0645\u0650 \u0627\u0644\u0644\u0651\u064e\u0647\u0650 \u0627\u0644\u0631\u0651\u064e\u062d\u0652\u0645\u064e\u0670\u0646\u0650 \u0627\u0644\u0631\u0651\u064e\u062d\u0650\u064a\u0645\u0650","transliteration":{"en":"Bismillaahir Rahmaanir Raheem"}},"translation":{"en":"In the name of Allah, the Entirely Merciful, the Especially Merciful.","id":"Dengan nama Allah Yang Maha Pengasih, Maha Penyayang."},"audio":{"primary":"https:\/\/cdn.alquran.cloud\/media\/audio\/ayah\/ar.alafasy\/1","secondary":["https:\/\/cdn.islamic.network\/quran\/audio\/128\/ar.alafasy\/1.mp3","https:\/\/cdn.islamic.network\/quran\/audio\/64\/ar.alafasy\/1.mp3"]}}},"relevation":{"arab":"\u0645\u0643\u0629","en":"Meccan","id":"Makkiyyah"},"tafsir":{"en":"TBD","id":"TBD"}},"text":{"arab":"\u064a\u064f\u0637\u064e\u0627\u0641\u064f \u0639\u064e\u0644\u064e\u064a\u0652\u0647\u0650\u0645\u0652 \u0628\u0650\u0643\u064e\u0623\u0652\u0633\u064d \u0645\u0651\u0650\u0646\u0652 \u0645\u0651\u064e\u0639\u0650\u064a\u0652\u0646\u064d\u06e2 \u06d9","transliteration":{"en":"Yutaafu 'alaihim bikaasim mim ma'een","id":"Yu\u1e6d\u0101fu \u2018alaihim bika'sim mim ma\u2018\u012bn(in)."}},"translation":{"en":"There will be circulated among them a cup [of wine] from a flowing spring,","id":"Diedarkan kepada mereka gelas yang berisi khamar dari sungai yang mengalir."},"audio":{"primary":"https:\/\/cdn.islamic.network\/quran\/audio\/128\/ar.alafasy\/3833.mp3","secondary":["https:\/\/cdn.islamic.network\/quran\/audio\/64\/ar.alafasy\/3833.mp3"]},"tafsir":{"id":{"short":"-","long":"-"}}},{"number":{"inQuran":3834,"inSurah":46},"meta":{"juz":23,"page":447,"manzil":6,"ruku":387,"hizbQuarter":179,"sajda":{"recommended":false,"obligatory":false}},"surah":{"number":37,"sequence":56,"numberOfVerses":182,"name":{"short":"\u0627\u0644\u0635\u0627\u0641\u0627\u062a","long":"\u0627\u0644\u0635\u0627\u0641\u0627\u062a","transliteration":{"en":"As-Saffat","id":"As-Saffat"},"translation":{"en":"Those who set the Ranks","id":"Barisan-barisan"}},"bismillah_pre":true,"preBismillah":{"preBismillah":{"text":{"arab":"\u0628\u0650\u0633\u0652\u0645\u0650 \u0627\u0644\u0644\u0651\u064e\u0647\u0650 \u0627\u0644\u0631\u0651\u064e\u062d\u0652\u0645\u064e\u0670\u0646\u0650 \u0627\u0644\u0631\u0651\u064e\u062d\u0650\u064a\u0645\u0650","transliteration":{"en":"Bismillaahir Rahmaanir Raheem"}},"translation":{"en":"In the name of Allah, the Entirely Merciful, the Especially Merciful.","id":"Dengan nama Allah Yang Maha Pengasih, Maha Penyayang."},"audio":{"primary":"https:\/\/cdn.alquran.cloud\/media\/audio\/ayah\/ar.alafasy\/1","secondary":["https:\/\/cdn.islamic.network\/quran\/audio\/128\/ar.alafasy\/1.mp3","https:\/\/cdn.islamic.network\/quran\/audio\/64\/ar.alafasy\/1.mp3"]}}},"relevation":{"arab":"\u0645\u0643\u0629","en":"Meccan","id":"Makkiyyah"},"tafsir":{"en":"TBD","id":"TBD"}},"text":{"arab":"\u0628\u064e\u064a\u0652\u0636\u064e\u0627\u06e4\u0621\u064e \u0644\u064e\u0630\u0651\u064e\u0629\u064d \u0644\u0651\u0650\u0644\u0634\u0651\u0670\u0631\u0650\u0628\u0650\u064a\u0652\u0646\u064e\u06da ","transliteration":{"en":"Baidaaa'a laz zatil lish shaaribeen","id":"Bai\u1e0d\u0101'a la\u017c\u017catil lisy-sy\u0101rib\u012bn(a)."}},"translation":{"en":"White and delicious to the drinkers;","id":"(Warnanya) putih bersih, sedap rasanya bagi orang-orang yang minum."},"audio":{"primary":"https:\/\/cdn.islamic.network\/quran\/audio\/128\/ar.alafasy\/3834.mp3","secondary":["https:\/\/cdn.islamic.network\/quran\/audio\/64\/ar.alafasy\/3834.mp3"]},"tafsir":{"id":{"short":"-","long":"-"}}},{"number":{"inQuran":3835,"inSurah":47},"meta":{"juz":23,"page":447,"manzil":6,"ruku":387,"hizbQuarter":179,"sajda":{"recommended":false,"obligatory":false}},"surah":{"number":37,"sequence":56,"numberOfVerses":182,"name":{"short":"\u0627\u0644\u0635\u0627\u0641\u0627\u062a","long":"\u0627\u0644\u0635\u0627\u0641\u0627\u062a","transliteration":{"en":"As-Saffat","id":"As-Saffat"},"translation":{"en":"Those who set the Ranks","id":"Barisan-barisan"}},"bismillah_pre":true,"preBismillah":{"preBismillah":{"text":{"arab":"\u0628\u0650\u0633\u0652\u0645\u0650 \u0627\u0644\u0644\u0651\u064e\u0647\u0650 \u0627\u0644\u0631\u0651\u064e\u062d\u0652\u0645\u064e\u0670\u0646\u0650 \u0627\u0644\u0631\u0651\u064e\u062d\u0650\u064a\u0645\u0650","transliteration":{"en":"Bismillaahir Rahmaanir Raheem"}},"translation":{"en":"In the name of Allah, the Entirely Merciful, the Especially Merciful.","id":"Dengan nama Allah Yang Maha Pengasih, Maha Penyayang."},"audio":{"primary":"https:\/\/cdn.alquran.cloud\/media\/audio\/ayah\/ar.alafasy\/1","secondary":["https:\/\/cdn.islamic.network\/quran\/audio\/128\/ar.alafasy\/1.mp3","https:\/\/cdn.islamic.network\/quran\/audio\/64\/ar.alafasy\/1.mp3"]}}},"relevation":{"arab":"\u0645\u0643\u0629","en":"Meccan","id":"Makkiyyah"},"tafsir":{"en":"TBD","id":"TBD"}},"text":{"arab":"\u0644\u064e\u0627 \u0641\u0650\u064a\u0652\u0647\u064e\u0627 \u063a\u064e\u0648\u0652\u0644\u064c \u0648\u0651\u064e\u0644\u064e\u0627 \u0647\u064f\u0645\u0652 \u0639\u064e\u0646\u0652\u0647\u064e\u0627 \u064a\u064f\u0646\u0652\u0632\u064e\u0641\u064f\u0648\u0652\u0646\u064e","transliteration":{"en":"Laa feehaa ghawlunw wa laa hum 'anhaa yunzafoon","id":"L\u0101 f\u012bh\u0101 gauluw wa l\u0101 hum \u2018anh\u0101 yunzaf\u016bn(a)."}},"translation":{"en":"No bad effect is there in it, nor from it will they be intoxicated.","id":"Tidak ada dalam khamar itu alkohol dan mereka tiada mabuk karenanya."},"audio":{"primary":"https:\/\/cdn.islamic.network\/quran\/audio\/128\/ar.alafasy\/3835.mp3","secondary":["https:\/\/cdn.islamic.network\/quran\/audio\/64\/ar.alafasy\/3835.mp3"]},"tafsir":{"id":{"short":"-","long":"-"}}},{"number":{"inQuran":3836,"inSurah":48},"meta":{"juz":23,"page":447,"manzil":6,"ruku":387,"hizbQuarter":179,"sajda":{"recommended":false,"obligatory":false}},"surah":{"number":37,"sequence":56,"numberOfVerses":182,"name":{"short":"\u0627\u0644\u0635\u0627\u0641\u0627\u062a","long":"\u0627\u0644\u0635\u0627\u0641\u0627\u062a","transliteration":{"en":"As-Saffat","id":"As-Saffat"},"translation":{"en":"Those who set the Ranks","id":"Barisan-barisan"}},"bismillah_pre":true,"preBismillah":{"preBismillah":{"text":{"arab":"\u0628\u0650\u0633\u0652\u0645\u0650 \u0627\u0644\u0644\u0651\u064e\u0647\u0650 \u0627\u0644\u0631\u0651\u064e\u062d\u0652\u0645\u064e\u0670\u0646\u0650 \u0627\u0644\u0631\u0651\u064e\u062d\u0650\u064a\u0645\u0650","transliteration":{"en":"Bismillaahir Rahmaanir Raheem"}},"translation":{"en":"In the name of Allah, the Entirely Merciful, the Especially Merciful.","id":"Dengan nama Allah Yang Maha Pengasih, Maha Penyayang."},"audio":{"primary":"https:\/\/cdn.alquran.cloud\/media\/audio\/ayah\/ar.alafasy\/1","secondary":["https:\/\/cdn.islamic.network\/quran\/audio\/128\/ar.alafasy\/1.mp3","https:\/\/cdn.islamic.network\/quran\/audio\/64\/ar.alafasy\/1.mp3"]}}},"relevation":{"arab":"\u0645\u0643\u0629","en":"Meccan","id":"Makkiyyah"},"tafsir":{"en":"TBD","id":"TBD"}},"text":{"arab":"\u0648\u064e\u0639\u0650\u0646\u0652\u062f\u064e\u0647\u064f\u0645\u0652 \u0642\u0670\u0635\u0650\u0631\u0670\u062a\u064f \u0627\u0644\u0637\u0651\u064e\u0631\u0652\u0641\u0650 \u0639\u0650\u064a\u0652\u0646\u064c \u06d9","transliteration":{"en":"Wa 'indahum qaasiraatut tarfi 'een","id":"Wa \u2018indahum q\u0101\u1e63ir\u0101tu\u1e6d-\u1e6darfi \u2018\u012bn(un)."}},"translation":{"en":"And with them will be women limiting [their] glances, with large, [beautiful] eyes,","id":"Di sisi mereka ada bidadari-bidadari yang tidak liar pandangannya dan jelita matanya,"},"audio":{"primary":"https:\/\/cdn.islamic.network\/quran\/audio\/128\/ar.alafasy\/3836.mp3","secondary":["https:\/\/cdn.islamic.network\/quran\/audio\/64\/ar.alafasy\/3836.mp3"]},"tafsir":{"id":{"short":"-","long":"-"}}},{"number":{"inQuran":3837,"inSurah":49},"meta":{"juz":23,"page":447,"manzil":6,"ruku":387,"hizbQuarter":179,"sajda":{"recommended":false,"obligatory":false}},"surah":{"number":37,"sequence":56,"numberOfVerses":182,"name":{"short":"\u0627\u0644\u0635\u0627\u0641\u0627\u062a","long":"\u0627\u0644\u0635\u0627\u0641\u0627\u062a","transliteration":{"en":"As-Saffat","id":"As-Saffat"},"translation":{"en":"Those who set the Ranks","id":"Barisan-barisan"}},"bismillah_pre":true,"preBismillah":{"preBismillah":{"text":{"arab":"\u0628\u0650\u0633\u0652\u0645\u0650 \u0627\u0644\u0644\u0651\u064e\u0647\u0650 \u0627\u0644\u0631\u0651\u064e\u062d\u0652\u0645\u064e\u0670\u0646\u0650 \u0627\u0644\u0631\u0651\u064e\u062d\u0650\u064a\u0645\u0650","transliteration":{"en":"Bismillaahir Rahmaanir Raheem"}},"translation":{"en":"In the name of Allah, the Entirely Merciful, the Especially Merciful.","id":"Dengan nama Allah Yang Maha Pengasih, Maha Penyayang."},"audio":{"primary":"https:\/\/cdn.alquran.cloud\/media\/audio\/ayah\/ar.alafasy\/1","secondary":["https:\/\/cdn.islamic.network\/quran\/audio\/128\/ar.alafasy\/1.mp3","https:\/\/cdn.islamic.network\/quran\/audio\/64\/ar.alafasy\/1.mp3"]}}},"relevation":{"arab":"\u0645\u0643\u0629","en":"Meccan","id":"Makkiyyah"},"tafsir":{"en":"TBD","id":"TBD"}},"text":{"arab":"\u0643\u064e\u0627\u064e\u0646\u0651\u064e\u0647\u064f\u0646\u0651\u064e \u0628\u064e\u064a\u0652\u0636\u064c \u0645\u0651\u064e\u0643\u0652\u0646\u064f\u0648\u0652\u0646\u064c","transliteration":{"en":"Ka annahunna baidum maknoon","id":"Ka'annahum bai\u1e0dum makn\u016bn(un)."}},"translation":{"en":"As if they were [delicate] eggs, well-protected.","id":"seakan-akan mereka adalah telur (burung unta) yang tersimpan dengan baik."},"audio":{"primary":"https:\/\/cdn.islamic.network\/quran\/audio\/128\/ar.alafasy\/3837.mp3","secondary":["https:\/\/cdn.islamic.network\/quran\/audio\/64\/ar.alafasy\/3837.mp3"]},"tafsir":{"id":{"short":"-","long":"-"}}},{"number":{"inQuran":3838,"inSurah":50},"meta":{"juz":23,"page":447,"manzil":6,"ruku":387,"hizbQuarter":179,"sajda":{"recommended":false,"obligatory":false}},"surah":{"number":37,"sequence":56,"numberOfVerses":182,"name":{"short":"\u0627\u0644\u0635\u0627\u0641\u0627\u062a","long":"\u0627\u0644\u0635\u0627\u0641\u0627\u062a","transliteration":{"en":"As-Saffat","id":"As-Saffat"},"translation":{"en":"Those who set the Ranks","id":"Barisan-barisan"}},"bismillah_pre":true,"preBismillah":{"preBismillah":{"text":{"arab":"\u0628\u0650\u0633\u0652\u0645\u0650 \u0627\u0644\u0644\u0651\u064e\u0647\u0650 \u0627\u0644\u0631\u0651\u064e\u062d\u0652\u0645\u064e\u0670\u0646\u0650 \u0627\u0644\u0631\u0651\u064e\u062d\u0650\u064a\u0645\u0650","transliteration":{"en":"Bismillaahir Rahmaanir Raheem"}},"translation":{"en":"In the name of Allah, the Entirely Merciful, the Especially Merciful.","id":"Dengan nama Allah Yang Maha Pengasih, Maha Penyayang."},"audio":{"primary":"https:\/\/cdn.alquran.cloud\/media\/audio\/ayah\/ar.alafasy\/1","secondary":["https:\/\/cdn.islamic.network\/quran\/audio\/128\/ar.alafasy\/1.mp3","https:\/\/cdn.islamic.network\/quran\/audio\/64\/ar.alafasy\/1.mp3"]}}},"relevation":{"arab":"\u0645\u0643\u0629","en":"Meccan","id":"Makkiyyah"},"tafsir":{"en":"TBD","id":"TBD"}},"text":{"arab":"\u0641\u064e\u0627\u064e\u0642\u0652\u0628\u064e\u0644\u064e \u0628\u064e\u0639\u0652\u0636\u064f\u0647\u064f\u0645\u0652 \u0639\u064e\u0644\u0670\u0649 \u0628\u064e\u0639\u0652\u0636\u064d \u064a\u0651\u064e\u062a\u064e\u0633\u064e\u0627\u06e4\u0621\u064e\u0644\u064f\u0648\u0652\u0646\u064e","transliteration":{"en":"Fa aqbala ba'duhum 'alaa badiny yatasaaa 'aloon","id":"Fa'aqbala ba\u2018\u1e0duhum \u2018al\u0101 ba\u2018\u1e0diy yatas\u0101'al\u016bn(a)."}},"translation":{"en":"And they will approach one another, inquiring of each other.","id":"Lalu sebahagian mereka menghadap kepada sebahagian yang lain sambil bercakap-cakap."},"audio":{"primary":"https:\/\/cdn.islamic.network\/quran\/audio\/128\/ar.alafasy\/3838.mp3","secondary":["https:\/\/cdn.islamic.network\/quran\/audio\/64\/ar.alafasy\/3838.mp3"]},"tafsir":{"id":{"short":"-","long":"-"}}},{"number":{"inQuran":3839,"inSurah":51},"meta":{"juz":23,"page":447,"manzil":6,"ruku":387,"hizbQuarter":179,"sajda":{"recommended":false,"obligatory":false}},"surah":{"number":37,"sequence":56,"numberOfVerses":182,"name":{"short":"\u0627\u0644\u0635\u0627\u0641\u0627\u062a","long":"\u0627\u0644\u0635\u0627\u0641\u0627\u062a","transliteration":{"en":"As-Saffat","id":"As-Saffat"},"translation":{"en":"Those who set the Ranks","id":"Barisan-barisan"}},"bismillah_pre":true,"preBismillah":{"preBismillah":{"text":{"arab":"\u0628\u0650\u0633\u0652\u0645\u0650 \u0627\u0644\u0644\u0651\u064e\u0647\u0650 \u0627\u0644\u0631\u0651\u064e\u062d\u0652\u0645\u064e\u0670\u0646\u0650 \u0627\u0644\u0631\u0651\u064e\u062d\u0650\u064a\u0645\u0650","transliteration":{"en":"Bismillaahir Rahmaanir Raheem"}},"translation":{"en":"In the name of Allah, the Entirely Merciful, the Especially Merciful.","id":"Dengan nama Allah Yang Maha Pengasih, Maha Penyayang."},"audio":{"primary":"https:\/\/cdn.alquran.cloud\/media\/audio\/ayah\/ar.alafasy\/1","secondary":["https:\/\/cdn.islamic.network\/quran\/audio\/128\/ar.alafasy\/1.mp3","https:\/\/cdn.islamic.network\/quran\/audio\/64\/ar.alafasy\/1.mp3"]}}},"relevation":{"arab":"\u0645\u0643\u0629","en":"Meccan","id":"Makkiyyah"},"tafsir":{"en":"TBD","id":"TBD"}},"text":{"arab":"\u0642\u064e\u0627\u0644\u064e \u0642\u064e\u0627\u06e4\u0649\u0655\u0650\u0644\u064c \u0645\u0651\u0650\u0646\u0652\u0647\u064f\u0645\u0652 \u0627\u0650\u0646\u0651\u0650\u064a\u0652 \u0643\u064e\u0627\u0646\u064e \u0644\u0650\u064a\u0652 \u0642\u064e\u0631\u0650\u064a\u0652\u0646\u064c\u06d9","transliteration":{"en":"Qaala qaaa'ilum minhum innee kaana lee qareen","id":"Q\u0101la q\u0101'ilum minhum inn\u012b k\u0101na l\u012b qar\u012bn(un)."}},"translation":{"en":"A speaker among them will say, \"Indeed, I had a companion [on earth]","id":"Berkatalah salah seorang di antara mereka: \"Sesungguhnya aku dahulu (di dunia) mempunyai seorang teman,"},"audio":{"primary":"https:\/\/cdn.islamic.network\/quran\/audio\/128\/ar.alafasy\/3839.mp3","secondary":["https:\/\/cdn.islamic.network\/quran\/audio\/64\/ar.alafasy\/3839.mp3"]},"tafsir":{"id":{"short":"-","long":"-"}}}]